Workbook

Sheet basebid
A1: Project | D1: Project# | F1: DATE: | G1: Prepared BY | N1: 10 | O1: 1/2" | P1: 83 | Q1: ﻿#12 Thhn Stranded | T1: 108 | U1: #1 Thhn Stranded
A2: Elevator/Lobby/Corridors & Vacant Suite 3450 | D2: KM05 | F2: Todays Date | G2: KM | N2: 11 | O2: 3/4" | P2: 84 | Q2: #10 Thhn Stranded | T2: 109 | U2: #1/0 Thhn Stranded
A3: 120 N LaSalle | N3: 12 | O3: 1" | P3: 85 | Q3: #8 Thhn Stranded | T3: 110 | U3: #2/0 Thhn Stranded
A4: G.C. | N4: 13 | O4: 1-1/4" | P4: 86 | Q4: #6 Thhn Stranded | T4: 111 | U4: #3/0 Thhn Stranded
A5: Contact Name | N5: 14 | O5: 1-1/2" | P5: 87 | Q5: #4 Thhn Stranded | T5: 112 | U5: #4/0 Thhn Stranded
A6: Telephone - Fax | N6: 15 | O6: 2" | P6: 88 | Q6: #3 Thhn Stranded | T6: 113 | U6: #250 MCM Thhn Wire
N7: 16 | O7: 2-1/2" | P7: 89 | Q7: #2 Thhn Stranded | T7: 114 | U7: #300 MCM Thhn Wire
A8: MATERIAL | C8: QTY | D8: MAT UNIT | E8: per | F8: EXTENSION | G8: LBR UNIT | H8: per | I8: EXTENSION | J8: TOTAL | K8: $$/QTY | N8: 17 | O8: 3" | P8: 90 | Q8: #1 Thhn Stranded | T8: 115 | U8: #350 MCM Thhn Wire
N9: 18 | O9: 3-1/2" | P9: 91 | Q9: #1/0 Thhn Stranded | T9: 116 | U9: #400 MCM Thhn Wire
N10: 19 | O10: 4" | P10: 92 | Q10: #2/0 Thhn Stranded | T10: 117 | U10: #500 MCM Thhn Wire
A11: TEMP POWER | B11: =SUM(J12:J14) -> 0 | P11: 93 | Q11: #3/0 Thhn Stranded | T11: 118 | U11: #600 MCM Thhn Wire
A12: Temp power from ComEd permanent power | D12: =F326/100 -> 8285.2 | E12: Lot | F12: =+D12*C12 -> 0 | G12: =F326/10000 -> 82.852 | H12: Lot | I12: =+G12*C12 -> 0 | J12: =+(((I12*$I$323)+(F12*(1+$E$323)))*(1+$C$329)) -> 0 | K12: =IF(J12=0,0,J12/C12) -> 0 | P12: 94 | Q12: #4/0 Thhn Stranded | T12: 119 | U12: #750 MCM Thhn Wire
A13: Hook up of construction trailer | D13: 1500 | E13: Lot | F13: =+D13*C13 -> 0 | G13: 30 | H13: Lot | I13: =+G13*C13 -> 0 | J13: =+(((I13*$I$323)+(F13*(1+$E$323)))*(1+$C$329)) -> 0 | K13: =IF(J13=0,0,J13/C13) -> 0 | P13: 95 | Q13: #250 MCM Thhn Wire | T13: 120 | U13: #900 MCM Thhn Wire
P14: 96 | Q14: #300 MCM Thhn Wire
A15: ELECTRICAL SERVICE & DISTRIBUTION | B15: =SUM(J16:J158) -> 0 | K15: =IF(J15=0,0,J15/C15) -> 0 | P15: 97 | Q15: #350 MCM Thhn Wire
A16: ComEd pad | D16: 2000 | E16: E | F16: =+D16*C16 -> 0 | G16: 10 | H16: E | I16: =+G16*C16 -> 0 | J16: =+(((I16*$I$323)+(F16*(1+$E$323)))*(1+$C$329)) -> 0 | K16: =IF(J16=0,0,J16/C16) -> 0 | P16: 98 | Q16: #400 MCM Thhn Wire
A17: Rework existing panel for new loads | D17: 400 | E17: E | F17: =+D17*C17 -> 0 | G17: 4 | H17: E | I17: =+G17*C17 -> 0 | J17: =+(((I17*$I$323)+(F17*(1+$E$323)))*(1+$C$329)) -> 0 | K17: =IF(J17=0,0,J17/C17) -> 0 | P17: 99 | Q17: #500 MCM Thhn Wire
A18: 4000A., 277/480V., 3PH. Main switchboard w/ meter | D18: 35000 | E18: E | F18: =+D18*C18 -> 0 | G18: 124 | H18: E | I18: =+G18*C18 -> 0 | J18: =+(((I18*$I$323)+(F18*(1+$E$323)))*(1+$C$329)) -> 0 | K18: =IF(J18=0,0,J18/C18) -> 0 | P18: 100 | Q18: #600 MCM Thhn Wire
B19: CU feed (ft) | D19: =((FEEDERS!$D$100*4)/10+FEEDERS!$D$19)*10 -> 79342.9 | E19: C | F19: =+(D19*C19)/100 -> 0 | G19: =((FEEDERS!$G$100*4)/10+FEEDERS!$G$19)*10 -> 335.75 | H19: C | I19: =+(G19*C19)/100 -> 0 | J19: =+(((I19*$I$323)+(F19*(1+$E$323)))*(1+$C$329)) -> 0 | K19: =IF(J19=0,0,J19/C19) -> 0 | P19: 101 | Q19: #750 MCM Thhn Wire
B20: AL feed (ft) | D20: =((FEEDERS!$D$119*4)/10+FEEDERS!$D$19)*11 -> 34010.79 | E20: C | F20: =+(D20*C20)/100 -> 0 | G20: =((FEEDERS!$G$119*4)/10+FEEDERS!$G$19)*11 -> 347.325 | H20: C | I20: =+(G20*C20)/100 -> 0 | J20: =+(((I20*$I$323)+(F20*(1+$E$323)))*(1+$C$329)) -> 0 | K20: =IF(J20=0,0,J20/C20) -> 0
A21: 3000A., 277/480V., 3PH. Main switchboard w/ meter | D21: 30000 | E21: E | F21: =+D21*C21 -> 0 | G21: 104 | H21: E | I21: =+G21*C21 -> 0 | J21: =+(((I21*$I$323)+(F21*(1+$E$323)))*(1+$C$329)) -> 0 | K21: =IF(J21=0,0,J21/C21) -> 0
B22: CU feed (ft) | D22: =((FEEDERS!$D$99*4)/10+FEEDERS!$D$19)*8 -> 53390.96 | E22: C | F22: =+(D22*C22)/100 -> 0 | G22: =((FEEDERS!$G$99*4)/10+FEEDERS!$G$19)*8 -> 255.8 | H22: C | I22: =+(G22*C22)/100 -> 0 | J22: =+(((I22*$I$323)+(F22*(1+$E$323)))*(1+$C$329)) -> 0 | K22: =IF(J22=0,0,J22/C22) -> 0
B23: AL feed (ft) | D23: =((FEEDERS!$D$119*4)/10+FEEDERS!$D$19)*8 -> 24735.12 | E23: C | F23: =+(D23*C23)/100 -> 0 | G23: =((FEEDERS!$G$119*4)/10+FEEDERS!$G$19)*8 -> 252.6 | H23: C | I23: =+(G23*C23)/100 -> 0 | J23: =+(((I23*$I$323)+(F23*(1+$E$323)))*(1+$C$329)) -> 0 | K23: =IF(J23=0,0,J23/C23) -> 0
A24: 2500A., 277/480V., 3PH. Main switchboard w/ meter | D24: 25000 | E24: E | F24: =+D24*C24 -> 0 | G24: 82 | H24: E | I24: =+G24*C24 -> 0 | J24: =+(((I24*$I$323)+(F24*(1+$E$323)))*(1+$C$329)) -> 0 | K24: =IF(J24=0,0,J24/C24) -> 0
B25: CU feed (ft) | D25: =((FEEDERS!$D$100*4)/10+FEEDERS!$D$19)*6 -> 47605.74 | E25: C | F25: =+(D25*C25)/100 -> 0 | G25: =((FEEDERS!$G$100*4)/10+FEEDERS!$G$19)*6 -> 201.45 | H25: C | I25: =+(G25*C25)/100 -> 0 | J25: =+(((I25*$I$323)+(F25*(1+$E$323)))*(1+$C$329)) -> 0 | K25: =IF(J25=0,0,J25/C25) -> 0
B26: AL feed (ft) | D26: =((FEEDERS!$D$119*4)/10+FEEDERS!$D$19)*7 -> 21643.23 | E26: C | F26: =+(D26*C26)/100 -> 0 | G26: =((FEEDERS!$G$119*4)/10+FEEDERS!$G$19)*7 -> 221.025 | H26: C | I26: =+(G26*C26)/100 -> 0 | J26: =+(((I26*$I$323)+(F26*(1+$E$323)))*(1+$C$329)) -> 0 | K26: =IF(J26=0,0,J26/C26) -> 0 | U26: k
A27: 2000A., 277/480V., 3PH. Main switchboard w/ meter | D27: 23000 | E27: E | F27: =+D27*C27 -> 0 | G27: 66 | H27: E | I27: =+G27*C27 -> 0 | J27: =+(((I27*$I$323)+(F27*(1+$E$323)))*(1+$C$329)) -> 0 | K27: =IF(J27=0,0,J27/C27) -> 0
B28: CU feed (ft) | D28: =((FEEDERS!$D$100*4)/10+FEEDERS!$D$19)*5 -> 39671.45 | E28: C | F28: =+(D28*C28)/100 -> 0 | G28: =((FEEDERS!$G$100*4)/10+FEEDERS!$G$19)*5 -> 167.875 | H28: C | I28: =+(G28*C28)/100 -> 0 | J28: =+(((I28*$I$323)+(F28*(1+$E$323)))*(1+$C$329)) -> 0 | K28: =IF(J28=0,0,J28/C28) -> 0
B29: AL feed (ft) | D29: =((FEEDERS!$D$118*4)/10+FEEDERS!$D$19)*6 -> 16876.86 | E29: C | F29: =+(D29*C29)/100 -> 0 | G29: =((FEEDERS!$G$118*4)/10+FEEDERS!$G$19)*6 -> 182.25 | H29: C | I29: =+(G29*C29)/100 -> 0 | J29: =+(((I29*$I$323)+(F29*(1+$E$323)))*(1+$C$329)) -> 0 | K29: =IF(J29=0,0,J29/C29) -> 0
A30: 1600A., 277/480V., 3PH. Main switchboard w/ meter | D30: 20000 | E30: E | F30: =+D30*C30 -> 0 | G30: 55 | H30: E | I30: =+G30*C30 -> 0 | J30: =+(((I30*$I$323)+(F30*(1+$E$323)))*(1+$C$329)) -> 0 | K30: =IF(J30=0,0,J30/C30) -> 0
B31: CU feed (ft) | D31: =((FEEDERS!$D$100*4)/10+FEEDERS!$D$19)*4 -> 31737.16 | E31: C | F31: =+(D31*C31)/100 -> 0 | G31: =((FEEDERS!$G$100*4)/10+FEEDERS!$G$19)*4 -> 134.3 | H31: C | I31: =+(G31*C31)/100 -> 0 | J31: =+(((I31*$I$323)+(F31*(1+$E$323)))*(1+$C$329)) -> 0 | K31: =IF(J31=0,0,J31/C31) -> 0
B32: AL feed (ft) | D32: =((FEEDERS!$D$118*4)/10+FEEDERS!$D$19)*5 -> 14064.05 | E32: C | F32: =+(D32*C32)/100 -> 0 | G32: =((FEEDERS!$G$118*4)/10+FEEDERS!$G$19)*5 -> 151.875 | H32: C | I32: =+(G32*C32)/100 -> 0 | J32: =+(((I32*$I$323)+(F32*(1+$E$323)))*(1+$C$329)) -> 0 | K32: =IF(J32=0,0,J32/C32) -> 0
A33: 1200A., 277/480V., 3PH. Main distribution board w/ ct/meter | D33: 17000 | E33: E | F33: =+D33*C33 -> 0 | G33: 51 | H33: E | I33: =+G33*C33 -> 0 | J33: =+(((I33*$I$323)+(F33*(1+$E$323)))*(1+$C$329)) -> 0 | K33: =IF(J33=0,0,J33/C33) -> 0
B34: CU feed (ft) | D34: =((FEEDERS!$D$100*4)/10+FEEDERS!$D$19)*3 -> 23802.87 | E34: C | F34: =+(D34*C34)/100 -> 0 | G34: =((FEEDERS!$G$100*4)/10+FEEDERS!$G$19)*3 -> 100.725 | H34: C | I34: =+(G34*C34)/100 -> 0 | J34: =+(((I34*$I$323)+(F34*(1+$E$323)))*(1+$C$329)) -> 0 | K34: =IF(J34=0,0,J34/C34) -> 0
B35: AL feed (ft) | D35: =((FEEDERS!$D$117*4)/10+FEEDERS!$D$17)*4 -> 8974.88 | E35: C | F35: =+(D35*C35)/100 -> 0 | G35: =((FEEDERS!$G$117*4)/10+FEEDERS!$G$17)*4 -> 95.6 | H35: C | I35: =+(G35*C35)/100 -> 0 | J35: =+(((I35*$I$323)+(F35*(1+$E$323)))*(1+$C$329)) -> 0 | K35: =IF(J35=0,0,J35/C35) -> 0
A36: 1000A., 277/480V., 3PH. Main distribution board w/ ct/meter | D36: 15000 | E36: E | F36: =+D36*C36 -> 0 | G36: 41 | H36: E | I36: =+G36*C36 -> 0 | J36: =+(((I36*$I$323)+(F36*(1+$E$323)))*(1+$C$329)) -> 0 | K36: =IF(J36=0,0,J36/C36) -> 0
B37: CU feed (ft) | D37: =((FEEDERS!$D$98*4)/10+FEEDERS!$D$17)*3 -> 16171.08 | E37: C | F37: =+(D37*C37)/100 -> 0 | G37: =((FEEDERS!$G$98*4)/10+FEEDERS!$G$17)*3 -> 75.3 | H37: C | I37: =+(G37*C37)/100 -> 0 | J37: =+(((I37*$I$323)+(F37*(1+$E$323)))*(1+$C$329)) -> 0 | K37: =IF(J37=0,0,J37/C37) -> 0
B38: AL feed (ft) | D38: =((FEEDERS!$D$118*4)/10+FEEDERS!$D$19)*3 -> 8438.43 | E38: C | F38: =+(D38*C38)/100 -> 0 | G38: =((FEEDERS!$G$118*4)/10+FEEDERS!$G$19)*3 -> 91.125 | H38: C | I38: =+(G38*C38)/100 -> 0 | J38: =+(((I38*$I$323)+(F38*(1+$E$323)))*(1+$C$329)) -> 0 | K38: =IF(J38=0,0,J38/C38) -> 0
A39: 800A., 277/480V., 3PH. Distribution board w/ feed | D39: 9000 | E39: E | F39: =+D39*C39 -> 0 | G39: 33 | H39: E | I39: =+G39*C39 -> 0 | J39: =+(((I39*$I$323)+(F39*(1+$E$323)))*(1+$C$329)) -> 0 | K39: =IF(J39=0,0,J39/C39) -> 0
B40: 600 CU feed (ft) | D40: =((FEEDERS!$D$100*4)/10+FEEDERS!$D$19)*2 -> 15868.58 | E40: C | F40: =+(D40*C40)/100 -> 0 | G40: =((FEEDERS!$G$100*4)/10+FEEDERS!$G$19)*2 -> 67.15 | H40: C | I40: =+(G40*C40)/100 -> 0 | J40: =+(((I40*$I$323)+(F40*(1+$E$323)))*(1+$C$329)) -> 0 | K40: =IF(J40=0,0,J40/C40) -> 0
B41: 500 CU feed (ft) | D41: =((FEEDERS!$D$99*4)/10+FEEDERS!$D$19)*2 -> 13347.74 | E41: C | F41: =+(D41*C41)/100 -> 0 | G41: =((FEEDERS!$G$99*4)/10+FEEDERS!$G$19)*2 -> 63.95 | H41: C | I41: =+(G41*C41)/100 -> 0 | J41: =+(((I41*$I$323)+(F41*(1+$E$323)))*(1+$C$329)) -> 0 | K41: =IF(J41=0,0,J41/C41) -> 0
B42: AL feed (ft) | D42: =((FEEDERS!$D$116*4)/10+FEEDERS!$D$16)*3 -> 5775.9 | E42: C | F42: =+(D42*C42)/100 -> 0 | G42: =((FEEDERS!$G$116*4)/10+FEEDERS!$G$16)*3 -> 66.3 | H42: C | I42: =+(G42*C42)/100 -> 0 | J42: =+(((I42*$I$323)+(F42*(1+$E$323)))*(1+$C$329)) -> 0 | K42: =IF(J42=0,0,J42/C42) -> 0
A43: 600A., 277/480V., 3PH. Main distribution board w/ ct/meter | D43: 8000 | E43: E | F43: =+D43*C43 -> 0 | G43: 28 | H43: E | I43: =+G43*C43 -> 0 | J43: =+(((I43*$I$323)+(F43*(1+$E$323)))*(1+$C$329)) -> 0 | K43: =IF(J43=0,0,J43/C43) -> 0
B44: CU feed (ft) | D44: =((FEEDERS!$D$97*4)/10+FEEDERS!$D$17)*2 -> 9779.44 | E44: C | F44: =+(D44*C44)/100 -> 0 | G44: =((FEEDERS!$G$97*4)/10+FEEDERS!$G$17)*2 -> 48.6 | H44: C | I44: =+(G44*C44)/100 -> 0 | J44: =+(((I44*$I$323)+(F44*(1+$E$323)))*(1+$C$329)) -> 0 | K44: =IF(J44=0,0,J44/C44) -> 0
B45: AL feed (ft) | D45: =((FEEDERS!$D$117*4)/10+FEEDERS!$D$17)*2 -> 4487.44 | E45: C | F45: =+(D45*C45)/100 -> 0 | G45: =((FEEDERS!$G$117*4)/10+FEEDERS!$G$17)*2 -> 47.8 | H45: C | I45: =+(G45*C45)/100 -> 0 | J45: =+(((I45*$I$323)+(F45*(1+$E$323)))*(1+$C$329)) -> 0 | K45: =IF(J45=0,0,J45/C45) -> 0
A46: 400A 277/480V., 3Ph, Panelboard w/ feed | D46: 3000 | E46: E | F46: =+D46*C46 -> 0 | G46: 14 | H46: E | I46: =+G46*C46 -> 0 | J46: =+(((I46*$I$323)+(F46*(1+$E$323)))*(1+$C$329)) -> 0 | K46: =IF(J46=0,0,J46/C46) -> 0
B47: 600 CU feed (ft) | D47: =(FEEDERS!$D$100*4)/10+FEEDERS!$D$19 -> 7934.29 | E47: C | F47: =+(D47*C47)/100 -> 0 | G47: =(FEEDERS!$G$100*4)/10+FEEDERS!$G$19 -> 33.575 | H47: C | I47: =+(G47*C47)/100 -> 0 | J47: =+(((I47*$I$323)+(F47*(1+$E$323)))*(1+$C$329)) -> 0 | K47: =IF(J47=0,0,J47/C47) -> 0
B48: 500 CU feed (ft) | D48: =(FEEDERS!$D$99*4)/10+FEEDERS!$D$19 -> 6673.87 | E48: C | F48: =+(D48*C48)/100 -> 0 | G48: =(FEEDERS!$G$99*4)/10+FEEDERS!$G$19 -> 31.975 | H48: C | I48: =+(G48*C48)/100 -> 0 | J48: =+(((I48*$I$323)+(F48*(1+$E$323)))*(1+$C$329)) -> 0 | K48: =IF(J48=0,0,J48/C48) -> 0
B49: 2- 250 AL feed (ft) | D49: =((FEEDERS!$D$113*4)/10+FEEDERS!$D$16)*2 -> 3145.84 | E49: C | F49: =+(D49*C49)/100 -> 0 | G49: =((FEEDERS!$G$113*4)/10+FEEDERS!$G$16)*2 -> 40.2 | H49: C | I49: =+(G49*C49)/100 -> 0 | J49: =+(((I49*$I$323)+(F49*(1+$E$323)))*(1+$C$329)) -> 0 | K49: =IF(J49=0,0,J49/C49) -> 0
B50: 750 AL feed (ft) | D50: =(FEEDERS!$D$119*4)/10+FEEDERS!$D$19 -> 3091.89 | E50: C | F50: =+(D50*C50)/100 -> 0 | G50: =(FEEDERS!$G$119*4)/10+FEEDERS!$G$19 -> 31.575 | H50: C | I50: =+(G50*C50)/100 -> 0 | J50: =+(((I50*$I$323)+(F50*(1+$E$323)))*(1+$C$329)) -> 0 | K50: =IF(J50=0,0,J50/C50) -> 0
A51: 250A 277/480V., 3PH Panelboard w/ feed | D51: 2300 | E51: E | F51: =+D51*C51 -> 0 | G51: 12 | H51: E | I51: =+G51*C51 -> 0 | J51: =+(((I51*$I$323)+(F51*(1+$E$323)))*(1+$C$329)) -> 0 | K51: =IF(J51=0,0,J51/C51) -> 0
B52: CU feed (ft) | D52: =(FEEDERS!$D$95*4)/10+FEEDERS!$D$16 -> 3616.64 | E52: C | F52: =+(D52*C52)/100 -> 0 | G52: =(FEEDERS!$G$95*4)/10+FEEDERS!$G$16 -> 20.9 | H52: C | I52: =+(G52*C52)/100 -> 0 | J52: =+(((I52*$I$323)+(F52*(1+$E$323)))*(1+$C$329)) -> 0 | K52: =IF(J52=0,0,J52/C52) -> 0
B53: AL feed (ft) | D53: =(FEEDERS!$D$115*4)/10+FEEDERS!$D$16 -> 1795.1 | E53: C | F53: =+(D53*C53)/100 -> 0 | G53: =(FEEDERS!$G$115*4)/10+FEEDERS!$G$16 -> 21.3 | H53: C | I53: =+(G53*C53)/100 -> 0 | J53: =+(((I53*$I$323)+(F53*(1+$E$323)))*(1+$C$329)) -> 0 | K53: =IF(J53=0,0,J53/C53) -> 0
A54: 225A 277/480V., 3PH Panelboard w/ feed | D54: 2300 | E54: E | F54: =+D54*C54 -> 0 | G54: 12 | H54: E | I54: =+G54*C54 -> 0 | J54: =+(((I54*$I$323)+(F54*(1+$E$323)))*(1+$C$329)) -> 0 | K54: =IF(J54=0,0,J54/C54) -> 0
B55: CU feed (ft) | D55: =(FEEDERS!$D$94*4)/10+FEEDERS!$D$16 -> 3261.32 | E55: C | F55: =+(D55*C55)/100 -> 0 | G55: =(FEEDERS!$G$94*4)/10+FEEDERS!$G$16 -> 19.7 | H55: C | I55: =+(G55*C55)/100 -> 0 | J55: =+(((I55*$I$323)+(F55*(1+$E$323)))*(1+$C$329)) -> 0 | K55: =IF(J55=0,0,J55/C55) -> 0
B56: AL feed (ft) | D56: =(FEEDERS!$D$114*4)/10+FEEDERS!$D$16 -> 1782.5 | E56: C | F56: =+(D56*C56)/100 -> 0 | G56: =(FEEDERS!$G$114*4)/10+FEEDERS!$G$16 -> 20.5 | H56: C | I56: =+(G56*C56)/100 -> 0 | J56: =+(((I56*$I$323)+(F56*(1+$E$323)))*(1+$C$329)) -> 0 | K56: =IF(J56=0,0,J56/C56) -> 0
A57: 200A 277/480V., 3PH Panelboard w/ feed | D57: 2300 | E57: E | F57: =+D57*C57 -> 0 | G57: 12 | H57: E | I57: =+G57*C57 -> 0 | J57: =+(((I57*$I$323)+(F57*(1+$E$323)))*(1+$C$329)) -> 0 | K57: =IF(J57=0,0,J57/C57) -> 0
B58: CU feed (ft) | D58: =(FEEDERS!$D$93*4)/10+FEEDERS!$D$15 -> 2492.79 | E58: C | F58: =+(D58*C58)/100 -> 0 | G58: =(FEEDERS!$G$93*4)/10+FEEDERS!$G$15 -> 18.013 | H58: C | I58: =+(G58*C58)/100 -> 0 | J58: =+(((I58*$I$323)+(F58*(1+$E$323)))*(1+$C$329)) -> 0 | K58: =IF(J58=0,0,J58/C58) -> 0
B59: AL feed (ft) | D59: =(FEEDERS!$D$113*4)/10+FEEDERS!$D$16 -> 1572.92 | E59: C | F59: =+(D59*C59)/100 -> 0 | G59: =(FEEDERS!$G$113*4)/10+FEEDERS!$G$16 -> 20.1 | H59: C | I59: =+(G59*C59)/100 -> 0 | J59: =+(((I59*$I$323)+(F59*(1+$E$323)))*(1+$C$329)) -> 0 | K59: =IF(J59=0,0,J59/C59) -> 0
A60: 100A 277/480V., 3PH Panelboard w/ feed | D60: 2000 | E60: E | F60: =+D60*C60 -> 0 | G60: 10 | H60: E | I60: =+G60*C60 -> 0 | J60: =+(((I60*$I$323)+(F60*(1+$E$323)))*(1+$C$329)) -> 0 | K60: =IF(J60=0,0,J60/C60) -> 0
B61: CU feed (ft) | D61: =(FEEDERS!$D$88*4)/10+FEEDERS!$D$13 -> 1181.04 | E61: C | F61: =+(D61*C61)/100 -> 0 | G61: =(FEEDERS!$G$88*4)/10+FEEDERS!$G$13 -> 11.782 | H61: C | I61: =+(G61*C61)/100 -> 0 | J61: =+(((I61*$I$323)+(F61*(1+$E$323)))*(1+$C$329)) -> 0 | K61: =IF(J61=0,0,J61/C61) -> 0
B62: AL feed (ft) | D62: =(FEEDERS!$D$108*4)/10+FEEDERS!$D$13 -> 753.9 | E62: C | F62: =+(D62*C62)/100 -> 0 | G62: =(FEEDERS!$G$108*4)/10+FEEDERS!$G$13 -> 12.982 | H62: C | I62: =+(G62*C62)/100 -> 0 | J62: =+(((I62*$I$323)+(F62*(1+$E$323)))*(1+$C$329)) -> 0 | K62: =IF(J62=0,0,J62/C62) -> 0
A63: 400A 120/208V., 3Ph, Panelboard w/ feed | D63: 3000 | E63: E | F63: =+D63*C63 -> 0 | G63: 14 | H63: E | I63: =+G63*C63 -> 0 | J63: =+(((I63*$I$323)+(F63*(1+$E$323)))*(1+$C$329)) -> 0 | K63: =IF(J63=0,0,J63/C63) -> 0
B64: 600 CU feed (ft) | D64: =(FEEDERS!$D$100*4)/10+FEEDERS!$D$19 -> 7934.29 | E64: C | F64: =+(D64*C64)/100 -> 0 | G64: =(FEEDERS!$G$100*4)/10+FEEDERS!$G$19 -> 33.575 | H64: C | I64: =+(G64*C64)/100 -> 0 | J64: =+(((I64*$I$323)+(F64*(1+$E$323)))*(1+$C$329)) -> 0 | K64: =IF(J64=0,0,J64/C64) -> 0
B65: 500 CU feed (ft) | D65: =(FEEDERS!$D$99*4)/10+FEEDERS!$D$19 -> 6673.87 | E65: C | F65: =+(D65*C65)/100 -> 0 | G65: =(FEEDERS!$G$99*4)/10+FEEDERS!$G$19 -> 31.975 | H65: C | I65: =+(G65*C65)/100 -> 0 | J65: =+(((I65*$I$323)+(F65*(1+$E$323)))*(1+$C$329)) -> 0 | K65: =IF(J65=0,0,J65/C65) -> 0
B66: 2- 250 AL feed (ft) | D66: =((FEEDERS!$D$113*4)/10+FEEDERS!$D$16)*2 -> 3145.84 | E66: C | F66: =+(D66*C66)/100 -> 0 | G66: =((FEEDERS!$G$113*4)/10+FEEDERS!$G$16)*2 -> 40.2 | H66: C | I66: =+(G66*C66)/100 -> 0 | J66: =+(((I66*$I$323)+(F66*(1+$E$323)))*(1+$C$329)) -> 0 | K66: =IF(J66=0,0,J66/C66) -> 0
B67: 750 AL feed (ft) | D67: =(FEEDERS!$D$119*4)/10+FEEDERS!$D$19 -> 3091.89 | E67: C | F67: =+(D67*C67)/100 -> 0 | G67: =(FEEDERS!$G$119*4)/10+FEEDERS!$G$19 -> 31.575 | H67: C | I67: =+(G67*C67)/100 -> 0 | J67: =+(((I67*$I$323)+(F67*(1+$E$323)))*(1+$C$329)) -> 0 | K67: =IF(J67=0,0,J67/C67) -> 0
A68: 200A 120/208V., 3PH Panelboard w/ feed | D68: 2300 | E68: E | F68: =+D68*C68 -> 0 | G68: 12 | H68: E | I68: =+G68*C68 -> 0 | J68: =+(((I68*$I$323)+(F68*(1+$E$323)))*(1+$C$329)) -> 0 | K68: =IF(J68=0,0,J68/C68) -> 0
B69: CU feed (ft) | D69: =(FEEDERS!$D$93*4)/10+FEEDERS!$D$15 -> 2492.79 | E69: C | F69: =+(D69*C69)/100 -> 0 | G69: =(FEEDERS!$G$93*4)/10+FEEDERS!$G$15 -> 18.013 | H69: C | I69: =+(G69*C69)/100 -> 0 | J69: =+(((I69*$I$323)+(F69*(1+$E$323)))*(1+$C$329)) -> 0 | K69: =IF(J69=0,0,J69/C69) -> 0
B70: AL feed (ft) | D70: =(FEEDERS!$D$113*4)/10+FEEDERS!$D$16 -> 1572.92 | E70: C | F70: =+(D70*C70)/100 -> 0 | G70: =(FEEDERS!$G$113*4)/10+FEEDERS!$G$16 -> 20.1 | H70: C | I70: =+(G70*C70)/100 -> 0 | J70: =+(((I70*$I$323)+(F70*(1+$E$323)))*(1+$C$329)) -> 0 | K70: =IF(J70=0,0,J70/C70) -> 0
A71: 150A 120/208V., 3PH Panelboard w/ feed | D71: 2000 | E71: E | F71: =+D71*C71 -> 0 | G71: 10 | H71: E | I71: =+G71*C71 -> 0 | J71: =+(((I71*$I$323)+(F71*(1+$E$323)))*(1+$C$329)) -> 0 | K71: =IF(J71=0,0,J71/C71) -> 0
B72: CU feed (ft) | D72: =(FEEDERS!$D$91*4)/10+FEEDERS!$D$14 -> 1774.5 | E72: C | F72: =+(D72*C72)/100 -> 0 | G72: =(FEEDERS!$G$91*4)/10+FEEDERS!$G$14 -> 14.742 | H72: C | I72: =+(G72*C72)/100 -> 0 | J72: =+(((I72*$I$323)+(F72*(1+$E$323)))*(1+$C$329)) -> 0 | K72: =IF(J72=0,0,J72/C72) -> 0
B73: AL feed (ft) | D73: =(FEEDERS!$D$111*4)/10+FEEDERS!$D$15 -> 1105.11 | E73: C | F73: =+(D73*C73)/100 -> 0 | G73: =(FEEDERS!$G$111*4)/10+FEEDERS!$G$15 -> 17.213 | H73: C | I73: =+(G73*C73)/100 -> 0 | J73: =+(((I73*$I$323)+(F73*(1+$E$323)))*(1+$C$329)) -> 0 | K73: =IF(J73=0,0,J73/C73) -> 0
A74: 125A 120/208V., 3PH Panelboard w/ feed | D74: 2000 | E74: E | F74: =+D74*C74 -> 0 | G74: 10 | H74: E | I74: =+G74*C74 -> 0 | J74: =+(((I74*$I$323)+(F74*(1+$E$323)))*(1+$C$329)) -> 0 | K74: =IF(J74=0,0,J74/C74) -> 0
B75: CU feed (ft) | D75: =(FEEDERS!$D$90*4)/10+FEEDERS!$D$13 -> 1449.84 | E75: C | F75: =+(D75*C75)/100 -> 0 | G75: =(FEEDERS!$G$90*4)/10+FEEDERS!$G$13 -> 12.582 | H75: C | I75: =+(G75*C75)/100 -> 0 | J75: =+(((I75*$I$323)+(F75*(1+$E$323)))*(1+$C$329)) -> 0 | K75: =IF(J75=0,0,J75/C75) -> 0
B76: AL feed (ft) | D76: =(FEEDERS!$D$110*4)/10+FEEDERS!$D$14 -> 947.52 | E76: C | F76: =+(D76*C76)/100 -> 0 | G76: =(FEEDERS!$G$110*4)/10+FEEDERS!$G$14 -> 15.142 | H76: C | I76: =+(G76*C76)/100 -> 0 | J76: =+(((I76*$I$323)+(F76*(1+$E$323)))*(1+$C$329)) -> 0 | K76: =IF(J76=0,0,J76/C76) -> 0
A77: 100A 120/208V., 3PH Panelboard w/ feed | D77: 2000 | E77: E | F77: =+D77*C77 -> 0 | G77: 10 | H77: E | I77: =+G77*C77 -> 0 | J77: =+(((I77*$I$323)+(F77*(1+$E$323)))*(1+$C$329)) -> 0 | K77: =IF(J77=0,0,J77/C77) -> 0
B78: CU feed (ft) | D78: =(FEEDERS!$D$88*4)/10+FEEDERS!$D$13 -> 1181.04 | E78: C | F78: =+(D78*C78)/100 -> 0 | G78: =(FEEDERS!$G$88*4)/10+FEEDERS!$G$13 -> 11.782 | H78: C | I78: =+(G78*C78)/100 -> 0 | J78: =+(((I78*$I$323)+(F78*(1+$E$323)))*(1+$C$329)) -> 0 | K78: =IF(J78=0,0,J78/C78) -> 0
B79: AL feed (ft) | D79: =(FEEDERS!$D$108*4)/10+FEEDERS!$D$13 -> 753.9 | E79: C | F79: =+(D79*C79)/100 -> 0 | G79: =(FEEDERS!$G$108*4)/10+FEEDERS!$G$13 -> 12.982 | H79: C | I79: =+(G79*C79)/100 -> 0 | J79: =+(((I79*$I$323)+(F79*(1+$E$323)))*(1+$C$329)) -> 0 | K79: =IF(J79=0,0,J79/C79) -> 0
A80: 300 KVA transformer | D80: 8000 | E80: E | F80: =+D80*C80 -> 0 | G80: 24 | H80: E | I80: =+G80*C80 -> 0 | J80: =+(((I80*$I$323)+(F80*(1+$E$323)))*(1+$C$329)) -> 0 | K80: =IF(J80=0,0,J80/C80) -> 0
A81: 225 KVA transformer | D81: 6500 | E81: E | F81: =+D81*C81 -> 0 | G81: 24 | H81: E | I81: =+G81*C81 -> 0 | J81: =+(((I81*$I$323)+(F81*(1+$E$323)))*(1+$C$329)) -> 0 | K81: =IF(J81=0,0,J81/C81) -> 0
B82: 600 CU feed (ft) | D82: =(FEEDERS!$D$100*4)/10+FEEDERS!$D$19 -> 7934.29 | E82: C | F82: =+(D82*C82)/100 -> 0 | G82: =(FEEDERS!$G$100*4)/10+FEEDERS!$G$19 -> 33.575 | H82: C | I82: =+(G82*C82)/100 -> 0 | J82: =+(((I82*$I$323)+(F82*(1+$E$323)))*(1+$C$329)) -> 0 | K82: =IF(J82=0,0,J82/C82) -> 0
B83: 500 CU feed (ft) | D83: =(FEEDERS!$D$99*4)/10+FEEDERS!$D$19 -> 6673.87 | E83: C | F83: =+(D83*C83)/100 -> 0 | G83: =(FEEDERS!$G$99*4)/10+FEEDERS!$G$19 -> 31.975 | H83: C | I83: =+(G83*C83)/100 -> 0 | J83: =+(((I83*$I$323)+(F83*(1+$E$323)))*(1+$C$329)) -> 0 | K83: =IF(J83=0,0,J83/C83) -> 0
B84: 2- 250 AL feed (ft) | D84: =((FEEDERS!$D$113*4)/10+FEEDERS!$D$16)*2 -> 3145.84 | E84: C | F84: =+(D84*C84)/100 -> 0 | G84: =((FEEDERS!$G$113*4)/10+FEEDERS!$G$16)*2 -> 40.2 | H84: C | I84: =+(G84*C84)/100 -> 0 | J84: =+(((I84*$I$323)+(F84*(1+$E$323)))*(1+$C$329)) -> 0 | K84: =IF(J84=0,0,J84/C84) -> 0
B85: 750 AL feed (ft) | D85: =(FEEDERS!$D$119*4)/10+FEEDERS!$D$19 -> 3091.89 | E85: C | F85: =+(D85*C85)/100 -> 0 | G85: =(FEEDERS!$G$119*4)/10+FEEDERS!$G$19 -> 31.575 | H85: C | I85: =+(G85*C85)/100 -> 0 | J85: =+(((I85*$I$323)+(F85*(1+$E$323)))*(1+$C$329)) -> 0 | K85: =IF(J85=0,0,J85/C85) -> 0
A86: 150 KVA transformer | D86: 5000 | E86: E | F86: =+D86*C86 -> 0 | G86: 15 | H86: E | I86: =+G86*C86 -> 0 | J86: =+(((I86*$I$323)+(F86*(1+$E$323)))*(1+$C$329)) -> 0 | K86: =IF(J86=0,0,J86/C86) -> 0
B87: CU feed (ft) | D87: =(FEEDERS!$D$94*3)/10+FEEDERS!$D$16 -> 2702.09 | E87: C | F87: =+(D87*C87)/100 -> 0 | G87: =(FEEDERS!$G$94*3)/10+FEEDERS!$G$16 -> 17.8 | H87: C | I87: =+(G87*C87)/100 -> 0 | J87: =+(((I87*$I$323)+(F87*(1+$E$323)))*(1+$C$329)) -> 0 | K87: =IF(J87=0,0,J87/C87) -> 0
B88: AL feed (ft) | D88: =(FEEDERS!$D$114*3)/10+FEEDERS!$D$16 -> 1592.975 | E88: C | F88: =+(D88*C88)/100 -> 0 | G88: =(FEEDERS!$G$114*3)/10+FEEDERS!$G$16 -> 18.4 | H88: C | I88: =+(G88*C88)/100 -> 0 | J88: =+(((I88*$I$323)+(F88*(1+$E$323)))*(1+$C$329)) -> 0 | K88: =IF(J88=0,0,J88/C88) -> 0
A89: 112.5KVA transformer | D89: 4000 | E89: E | F89: =+D89*C89 -> 0 | G89: 13 | H89: E | I89: =+G89*C89 -> 0 | J89: =+(((I89*$I$323)+(F89*(1+$E$323)))*(1+$C$329)) -> 0 | K89: =IF(J89=0,0,J89/C89) -> 0
B90: CU feed (ft) | D90: =(FEEDERS!$D$91*3)/10+FEEDERS!$D$14 -> 1486.275 | E90: C | F90: =+(D90*C90)/100 -> 0 | G90: =(FEEDERS!$G$91*3)/10+FEEDERS!$G$14 -> 13.442 | H90: C | I90: =+(G90*C90)/100 -> 0 | J90: =+(((I90*$I$323)+(F90*(1+$E$323)))*(1+$C$329)) -> 0 | K90: =IF(J90=0,0,J90/C90) -> 0
B91: AL feed (ft) | D91: =(FEEDERS!$D$111*3)/10+FEEDERS!$D$15 -> 1003.995 | E91: C | F91: =+(D91*C91)/100 -> 0 | G91: =(FEEDERS!$G$111*3)/10+FEEDERS!$G$15 -> 15.713 | H91: C | I91: =+(G91*C91)/100 -> 0 | J91: =+(((I91*$I$323)+(F91*(1+$E$323)))*(1+$C$329)) -> 0 | K91: =IF(J91=0,0,J91/C91) -> 0
A92: 75KVA transformer | D92: 3500 | E92: E | F92: =+D92*C92 -> 0 | G92: 13 | H92: E | I92: =+G92*C92 -> 0 | J92: =+(((I92*$I$323)+(F92*(1+$E$323)))*(1+$C$329)) -> 0 | K92: =IF(J92=0,0,J92/C92) -> 0
B93: CU feed (ft) | D93: =(FEEDERS!$D$90*3)/10+FEEDERS!$D$13 -> 1214.43 | E93: C | F93: =+(D93*C93)/100 -> 0 | G93: =(FEEDERS!$G$90*3)/10+FEEDERS!$G$13 -> 11.482 | H93: C | I93: =+(G93*C93)/100 -> 0 | J93: =+(((I93*$I$323)+(F93*(1+$E$323)))*(1+$C$329)) -> 0 | K93: =IF(J93=0,0,J93/C93) -> 0
B94: AL feed (ft) | D94: =(FEEDERS!$D$110*3)/10+FEEDERS!$D$14 -> 866.04 | E94: C | F94: =+(D94*C94)/100 -> 0 | G94: =(FEEDERS!$G$110*3)/10+FEEDERS!$G$14 -> 13.742 | H94: C | I94: =+(G94*C94)/100 -> 0 | J94: =+(((I94*$I$323)+(F94*(1+$E$323)))*(1+$C$329)) -> 0 | K94: =IF(J94=0,0,J94/C94) -> 0
A95: 45KVA transformer | D95: 2500 | E95: E | F95: =+D95*C95 -> 0 | G95: 12 | H95: E | I95: =+G95*C95 -> 0 | J95: =+(((I95*$I$323)+(F95*(1+$E$323)))*(1+$C$329)) -> 0 | K95: =IF(J95=0,0,J95/C95) -> 0
B96: CU feed (ft) | D96: =(FEEDERS!$D$87*3)/10+FEEDERS!$D$12 -> 731.3 | E96: C | F96: =+(D96*C96)/100 -> 0 | G96: =(FEEDERS!$G$87*3)/10+FEEDERS!$G$12 -> 9.488 | H96: C | I96: =+(G96*C96)/100 -> 0 | J96: =+(((I96*$I$323)+(F96*(1+$E$323)))*(1+$C$329)) -> 0 | K96: =IF(J96=0,0,J96/C96) -> 0
B97: AL feed (ft) | D97: 250 | E97: C | F97: =+(D97*C97)/100 -> 0 | G97: 9 | H97: C | I97: =+(G97*C97)/100 -> 0 | J97: =+(((I97*$I$323)+(F97*(1+$E$323)))*(1+$C$329)) -> 0 | K97: =IF(J97=0,0,J97/C97) -> 0
A98: 30KVA transformer | D98: 2000 | E98: E | F98: =+D98*C98 -> 0 | G98: 10 | H98: E | I98: =+G98*C98 -> 0 | J98: =+(((I98*$I$323)+(F98*(1+$E$323)))*(1+$C$329)) -> 0 | K98: =IF(J98=0,0,J98/C98) -> 0
B99: CU feed (ft) | D99: =(FEEDERS!$D$86*3)/10+FEEDERS!$D$11 -> 458.05 | E99: C | F99: =+(D99*C99)/100 -> 0 | G99: =(FEEDERS!$G$86*3)/10+FEEDERS!$G$11 -> 7.06 | H99: C | I99: =+(G99*C99)/100 -> 0 | J99: =+(((I99*$I$323)+(F99*(1+$E$323)))*(1+$C$329)) -> 0 | K99: =IF(J99=0,0,J99/C99) -> 0
B100: AL feed (ft) | D100: 150 | E100: C | F100: =+(D100*C100)/100 -> 0 | G100: 6 | H100: C | I100: =+(G100*C100)/100 -> 0 | J100: =+(((I100*$I$323)+(F100*(1+$E$323)))*(1+$C$329)) -> 0 | K100: =IF(J100=0,0,J100/C100) -> 0
...

Sheet FEEDERS
A1: Project | D1: Project# | F1: DATE: | G1: Prepared BY
A2: Job Name | D2: KM05 | F2: Todays Date | G2: KM
A3: Job Location
A4: G.C.
A5: Contact Name | M5: ELYSIA SHEET
A6: Telephone - Fax | M6: TAKE HIGHEST PRICE | S6: Aluminum Pricing
M7: PER 100 | Q7: Prevoius Price | S7: PER 1000
A8: MATERIAL | C8: QTY | D8: MAT UNIT | E8: per | F8: EXTENSION | G8: LBR UNIT | H8: per | I8: EXTENSION | J8: TOTAL | K8: $$/QTY | M8: 1/2-EMT | O8: 72 | Q8: 70 | R8: =(O8-Q8)/Q8 -> 0.028571429 | S8: #1 | U8: 450
A9: EMT Set Screw UNIT | J9: =+(((I9*$I$125)+(F9*(1+$E$125)))*(1+$C$131)) -> 0 | K9: =IF(J9=0,0,J9/C9) -> 0 | M9: 1/2-HW | O9: 338 | Q9: 331 | R9: =(O9-Q9)/Q9 -> 0.021148036 | S9: #1/0 | U9: 500
A10: 1/2" SS EMT Unit | B10: 0.5 | C10: 1 | D10: =O8*B10+O8 -> 108 | E10: C | F10: =+(D10*C10)/100 -> 1.08 | G10: 4.67 | H10: C | I10: =+(G10*C10)/100 -> 0.0467 | J10: =+(((I10*$I$125)+(F10*(1+$E$125)))*(1+$C$131)) -> 5.7673 | K10: =IF(J10=0,0,J10/C10) -> 5.7673 | M10: 1/2-IMC | O10: 203 | Q10: 199 | R10: =(O10-Q10)/Q10 -> 0.020100503 | S10: #2/0 | U10: 600
A11: 3/4" SS EMT Unit | B11: 0.45 | C11: 1 | D11: =O12*B11+O12 -> 184.15 | E11: C | F11: =+(D11*C11)/100 -> 1.8415 | G11: 4.96 | H11: C | I11: =+(G11*C11)/100 -> 0.0496 | J11: =+(((I11*$I$125)+(F11*(1+$E$125)))*(1+$C$131)) -> 6.8910538 | K11: =IF(J11=0,0,J11/C11) -> 6.8910538 | M11: 1/2-PVC40 | O11: 89 | Q11: 89 | R11: =(O11-Q11)/Q11 -> 0 | S11: #3/0 | U11: 700
A12: 1" SS EMT Unit | B12: 0.4 | C12: 1 | D12: =O16+B12*O16 -> 312.2 | E12: C | F12: =+(D12*C12)/100 -> 3.122 | G12: 6.938 | H12: C | I12: =+(G12*C12)/100 -> 0.06938 | J12: =+(((I12*$I$125)+(F12*(1+$E$125)))*(1+$C$131)) -> 10.241245 | K12: =IF(J12=0,0,J12/C12) -> 10.241245 | M12: 3/4-EMT | O12: 127 | Q12: 124 | R12: =(O12-Q12)/Q12 -> 0.024193548 | S12: #4/0 | U12: 800
A13: 1-1/4" SS EMT Unit | B13: 0.4 | C13: 1 | D13: =O20*B13+O20 -> 508.2 | E13: C | F13: =+(D13*C13)/100 -> 5.082 | G13: 8.182 | H13: C | I13: =+(G13*C13)/100 -> 0.08182 | J13: =+(((I13*$I$125)+(F13*(1+$E$125)))*(1+$C$131)) -> 13.621265 | K13: =IF(J13=0,0,J13/C13) -> 13.621265 | M13: 3/4-HW | O13: 346 | Q13: 339 | R13: =(O13-Q13)/Q13 -> 0.020648968 | S13: 250 MCM | U13: 950
A14: 1-1/2" SS EMT Unit | B14: 0.4 | C14: 1 | D14: =O24*B14+O24 -> 621.6 | E14: C | F14: =+(D14*C14)/100 -> 6.216 | G14: 9.542 | H14: C | I14: =+(G14*C14)/100 -> 0.09542 | J14: =+(((I14*$I$125)+(F14*(1+$E$125)))*(1+$C$131)) -> 16.2043 | K14: =IF(J14=0,0,J14/C14) -> 16.2043 | M14: 3/4-IMC | O14: 239 | Q14: 234 | R14: =(O14-Q14)/Q14 -> 0.021367521 | S14: 300 MCM | U14: 1300
A15: 2" SS EMT Unit | B15: 0.35 | C15: 1 | D15: =O28*B15+O28 -> 700.65 | E15: C | F15: =+(D15*C15)/100 -> 7.0065 | G15: 11.213 | H15: C | I15: =+(G15*C15)/100 -> 0.11213 | J15: =+(((I15*$I$125)+(F15*(1+$E$125)))*(1+$C$131)) -> 18.713406 | K15: =IF(J15=0,0,J15/C15) -> 18.713406 | M15: 3/4-PVC40 | O15: 108 | Q15: 108 | R15: =(O15-Q15)/Q15 -> 0 | S15: 350 MCM | U15: 1350
A16: 2-1/2" SS EMT Unit | B16: 0.3 | C16: 1 | D16: =O32*B16+O32 -> 1024.4 | E16: C | F16: =+(D16*C16)/100 -> 10.244 | G16: 12.1 | H16: C | I16: =+(G16*C16)/100 -> 0.121 | J16: =+(((I16*$I$125)+(F16*(1+$E$125)))*(1+$C$131)) -> 23.15201 | K16: =IF(J16=0,0,J16/C16) -> 23.15201 | M16: 1-EMT | O16: 223 | Q16: 219 | R16: =(O16-Q16)/Q16 -> 0.01826484 | S16: 400 MM | U16: 1550
A17: 3" SS EMT Unit | B17: 0.25 | C17: 1 | D17: =O36*B17+O36 -> 1250 | E17: C | F17: =+(D17*C17)/100 -> 12.5 | G17: 13.5 | H17: C | I17: =+(G17*C17)/100 -> 0.135 | J17: =+(((I17*$I$125)+(F17*(1+$E$125)))*(1+$C$131)) -> 27.01125 | K17: =IF(J17=0,0,J17/C17) -> 27.01125 | M17: 1-HW | O17: 552 | Q17: 540 | R17: =(O17-Q17)/Q17 -> 0.022222222 | S17: 500 MCM | U17: 1700
A18: 3-1/2" SS EMT Unit | B18: 0.2 | C18: 1 | D18: =O40*B18+O40 -> 1584 | E18: C | F18: =+(D18*C18)/100 -> 15.84 | G18: 16.355 | H18: C | I18: =+(G18*C18)/100 -> 0.16355 | J18: =+(((I18*$I$125)+(F18*(1+$E$125)))*(1+$C$131)) -> 33.4915 | K18: =IF(J18=0,0,J18/C18) -> 33.4915 | M18: 1-IMC | O18: 367 | Q18: 359 | R18: =(O18-Q18)/Q18 -> 0.022284123 | S18: 600 MCM | U18: 2200
A19: 4" SS EMT Unit | B19: 0.15 | C19: 1 | D19: =O44*B19+O44 -> 1553.65 | E19: C | F19: =+(D19*C19)/100 -> 15.5365 | G19: 18.775 | H19: C | I19: =+(G19*C19)/100 -> 0.18775 | J19: =+(((I19*$I$125)+(F19*(1+$E$125)))*(1+$C$131)) -> 35.528491 | K19: =IF(J19=0,0,J19/C19) -> 35.528491 | M19: 1-PVC40 | O19: 164 | Q19: 164 | R19: =(O19-Q19)/Q19 -> 0 | S19: 750 MCM | U19: 2600
J20: =+(((I20*$I$125)+(F20*(1+$E$125)))*(1+$C$131)) -> 0 | K20: =IF(J20=0,0,J20/C20) -> 0 | M20: 1-1/4-EMT | O20: 363 | Q20: 356 | R20: =(O20-Q20)/Q20 -> 0.019662921 | S20: 900 MCM | U20: 3500
A21: EMT Compression UNIT | J21: =+(((I21*$I$125)+(F21*(1+$E$125)))*(1+$C$131)) -> 0 | K21: =IF(J21=0,0,J21/C21) -> 0 | M21: 1-1/4-HW | O21: 813 | Q21: 795 | R21: =(O21-Q21)/Q21 -> 0.022641509
A22: 1/2" COMP EMT Unit | B22: 0.6 | C22: 1 | D22: =O8*B22+O8 -> 115.2 | E22: C | F22: =+(D22*C22)/100 -> 1.152 | G22: 4.79 | H22: C | I22: =+(G22*C22)/100 -> 0.0479 | J22: =+(((I22*$I$125)+(F22*(1+$E$125)))*(1+$C$131)) -> 5.96428 | K22: =IF(J22=0,0,J22/C22) -> 5.96428 | M22: 1-1/4-IMC | O22: 515 | Q22: 504 | R22: =(O22-Q22)/Q22 -> 0.021825397
A23: 3/4" COMP EMT Unit | B23: 0.55 | C23: 1 | D23: =O12*B23+O12 -> 196.85 | E23: C | F23: =+(D23*C23)/100 -> 1.9685 | G23: 5.065 | H23: C | I23: =+(G23*C23)/100 -> 0.05065 | J23: =+(((I23*$I$125)+(F23*(1+$E$125)))*(1+$C$131)) -> 7.1339713 | K23: =IF(J23=0,0,J23/C23) -> 7.1339713 | M23: 1-1/4-PVC40 | O23: 222 | Q23: 222 | R23: =(O23-Q23)/Q23 -> 0
A24: 1" COMP EMT Unit | B24: 0.5 | C24: 1 | D24: =O16*B24+O16 -> 334.5 | E24: C | F24: =+(D24*C24)/100 -> 3.345 | G24: 6.905 | H24: C | I24: =+(G24*C24)/100 -> 0.06905 | J24: =+(((I24*$I$125)+(F24*(1+$E$125)))*(1+$C$131)) -> 10.454763 | K24: =IF(J24=0,0,J24/C24) -> 10.454763 | M24: 1-1/2-EMT | O24: 444 | Q24: 435 | R24: =(O24-Q24)/Q24 -> 0.020689655
A25: 1-1/4" COMP EMT Unit | B25: 0.45 | C25: 1 | D25: =O22*B25+O22 -> 746.75 | E25: C | F25: =+(D25*C25)/100 -> 7.4675 | G25: 8.282 | H25: C | I25: =+(G25*C25)/100 -> 0.08282 | J25: =+(((I25*$I$125)+(F25*(1+$E$125)))*(1+$C$131)) -> 16.349279 | K25: =IF(J25=0,0,J25/C25) -> 16.349279 | M25: 1-1/2-HW | O25: 914 | Q25: 895 | R25: =(O25-Q25)/Q25 -> 0.02122905
A26: 1-1/2" COMP EMT Unit | B26: 0.4 | C26: 1 | D26: =O24*B26+O24 -> 621.6 | E26: C | F26: =+(D26*C26)/100 -> 6.216 | G26: 9.663 | H26: C | I26: =+(G26*C26)/100 -> 0.09663 | J26: =+(((I26*$I$125)+(F26*(1+$E$125)))*(1+$C$131)) -> 16.32288 | K26: =IF(J26=0,0,J26/C26) -> 16.32288 | M26: 1-1/2-IMC | O26: 641 | Q26: 627 | R26: =(O26-Q26)/Q26 -> 0.022328549
A27: 2" COMP EMT Unit | B27: 0.35 | C27: 1 | D27: =O28*B27+O28 -> 700.65 | E27: C | F27: =+(D27*C27)/100 -> 7.0065 | G27: 11.392 | H27: C | I27: =+(G27*C27)/100 -> 0.11392 | J27: =+(((I27*$I$125)+(F27*(1+$E$125)))*(1+$C$131)) -> 18.888826 | K27: =IF(J27=0,0,J27/C27) -> 18.888826 | M27: 1-1/2-PVC40 | O27: 257 | Q27: 257 | R27: =(O27-Q27)/Q27 -> 0
A28: 2-1/2" COMP EMT Unit | B28: 0.3 | C28: 1 | D28: =O32*B28+O32 -> 1024.4 | E28: C | F28: =+(D28*C28)/100 -> 10.244 | G28: 12.23 | H28: C | I28: =+(G28*C28)/100 -> 0.1223 | J28: =+(((I28*$I$125)+(F28*(1+$E$125)))*(1+$C$131)) -> 23.27941 | K28: =IF(J28=0,0,J28/C28) -> 23.27941 | M28: 2-EMT | O28: 519 | Q28: 509 | R28: =(O28-Q28)/Q28 -> 0.019646365
A29: 3" COMP EMT Unit | B29: 0.25 | C29: 1 | D29: =O36*B29+O36 -> 1250 | E29: C | F29: =+(D29*C29)/100 -> 12.5 | G29: 13.65 | H29: C | I29: =+(G29*C29)/100 -> 0.1365 | J29: =+(((I29*$I$125)+(F29*(1+$E$125)))*(1+$C$131)) -> 27.15825 | K29: =IF(J29=0,0,J29/C29) -> 27.15825 | M29: 2-HW | O29: 1121 | Q29: 1097 | R29: =(O29-Q29)/Q29 -> 0.021877849
A30: 3-1/2" COMP EMT Unit | B30: 0.2 | C30: 1 | D30: =O40*B30+O40 -> 1584 | E30: C | F30: =+(D30*C30)/100 -> 15.84 | G30: 16.535 | H30: C | I30: =+(G30*C30)/100 -> 0.16535 | J30: =+(((I30*$I$125)+(F30*(1+$E$125)))*(1+$C$131)) -> 33.6679 | K30: =IF(J30=0,0,J30/C30) -> 33.6679 | M30: 2-IMC | O30: 802 | Q30: 785 | R30: =(O30-Q30)/Q30 -> 0.021656051
A31: 4" COMP EMT Unit | B31: 0.3 | C31: 1 | D31: =O44*B31+O44 -> 1756.3 | E31: C | F31: =+(D31*C31)/100 -> 17.563 | G31: 18.975 | H31: C | I31: =+(G31*C31)/100 -> 0.18975 | J31: =+(((I31*$I$125)+(F31*(1+$E$125)))*(1+$C$131)) -> 37.958708 | K31: =IF(J31=0,0,J31/C31) -> 37.958708 | M31: 2-PVC40 | O31: 326 | Q31: 326 | R31: =(O31-Q31)/Q31 -> 0
M32: 2-1/2-EMT | O32: 788 | Q32: 772 | R32: =(O32-Q32)/Q32 -> 0.020725389 | S32: Romex labor rate / ft
A33: HW Unit | J33: =+(((I33*$I$125)+(F33*(1+$E$125)))*(1+$C$131)) -> 0 | K33: =IF(J33=0,0,J33/C33) -> 0 | M33: 2-1/2-HW | O33: 2112 | Q33: 2068 | R33: =(O33-Q33)/Q33 -> 0.021276596 | S33: 14/2: .012 .015 .018 | V33: 390 | W33: 456
A34: 1/2" HW Unit | B34: 0.5 | C34: 1 | D34: =O9*B34+O9 -> 507 | E34: C | F34: =+(D34*C34)/100 -> 5.07 | G34: 9.224 | H34: C | I34: =+(G34*C34)/100 -> 0.09224 | J34: =+(((I34*$I$125)+(F34*(1+$E$125)))*(1+$C$131)) -> 14.629195 | K34: =IF(J34=0,0,J34/C34) -> 14.629195 | M34: 2-1/2-IMC | O34: 1591 | Q34: 1557 | R34: =(O34-Q34)/Q34 -> 0.021836866 | S34: 12/2: .012 .015 .018 | W34: 675
A35: 3/4" HW Unit | B35: 0.45 | C35: 1 | D35: =O13*B35+O13 -> 501.7 | E35: C | F35: =+(D35*C35)/100 -> 5.017 | G35: 9.853 | H35: C | I35: =+(G35*C35)/100 -> 0.09853 | J35: =+(((I35*$I$125)+(F35*(1+$E$125)))*(1+$C$131)) -> 15.187182 | K35: =IF(J35=0,0,J35/C35) -> 15.187182 | M35: 2-1/2-PVC40 | O35: 506 | Q35: 506 | R35: =(O35-Q35)/Q35 -> 0 | S35: 10/2: .012 .015 .018
A36: 1" HW Unit | B36: 0.4 | C36: 1 | D36: =O17*B36+O17 -> 772.8 | E36: C | F36: =+(D36*C36)/100 -> 7.728 | G36: 10.823 | H36: C | I36: =+(G36*C36)/100 -> 0.10823 | J36: =+(((I36*$I$125)+(F36*(1+$E$125)))*(1+$C$131)) -> 19.12666 | K36: =IF(J36=0,0,J36/C36) -> 19.12666 | M36: 3-EMT | O36: 1000 | Q36: 979 | R36: =(O36-Q36)/Q36 -> 0.02145046 | S36: 14/3: .012 .015 .018 | W36: 637
A37: 1-1/4" HW Unit | B37: 0.4 | C37: 1 | D37: =O21*B37+O21 -> 1138.2 | E37: C | F37: =+(D37*C37)/100 -> 11.382 | G37: 14.625 | H37: C | I37: =+(G37*C37)/100 -> 0.14625 | J37: =+(((I37*$I$125)+(F37*(1+$E$125)))*(1+$C$131)) -> 26.881155 | K37: =IF(J37=0,0,J37/C37) -> 26.881155 | M37: 3-HW | O37: 2395 | Q37: 2344 | R37: =(O37-Q37)/Q37 -> 0.021757679 | S37: 12/3: .012 .015 .018 | W37: 927
A38: 1-1/2" HW Unit | B38: 0.4 | C38: 1 | D38: =O25*B38+O25 -> 1279.6 | E38: C | F38: =+(D38*C38)/100 -> 12.796 | G38: 16.46 | H38: C | I38: =+(G38*C38)/100 -> 0.1646 | J38: =+(((I38*$I$125)+(F38*(1+$E$125)))*(1+$C$131)) -> 30.23839 | K38: =IF(J38=0,0,J38/C38) -> 30.23839 | M38: 3-IMC | O38: 2082 | Q38: 2038 | R38: =(O38-Q38)/Q38 -> 0.021589794 | S38: 10/3: .012 .015 .018 | W38: 1538
A39: 2" HW Unit | B39: 0.35 | C39: 1 | D39: =O33*B39+O33 -> 2851.2 | E39: C | F39: =+(D39*C39)/100 -> 28.512 | G39: 18.948 | H39: C | I39: =+(G39*C39)/100 -> 0.18948 | J39: =+(((I39*$I$125)+(F39*(1+$E$125)))*(1+$C$131)) -> 50.00352 | K39: =IF(J39=0,0,J39/C39) -> 50.00352 | M39: 3-PVC40 | O39: 615 | Q39: 615 | R39: =(O39-Q39)/Q39 -> 0
A40: 2-1/2" HW Unit | B40: 0.3 | C40: 1 | D40: =O33*B40+O33 -> 2745.6 | E40: C | F40: =+(D40*C40)/100 -> 27.456 | G40: 19.997 | H40: C | I40: =+(G40*C40)/100 -> 0.19997 | J40: =+(((I40*$I$125)+(F40*(1+$E$125)))*(1+$C$131)) -> 49.8673 | K40: =IF(J40=0,0,J40/C40) -> 49.8673 | M40: 3-1/2-EMT | O40: 1320 | Q40: 1292 | R40: =(O40-Q40)/Q40 -> 0.021671827
A41: 3" HW Unit | B41: 0.25 | C41: 1 | D41: =O37*B41+O37 -> 2993.75 | E41: C | F41: =+(D41*C41)/100 -> 29.9375 | G41: 23.898 | H41: C | I41: =+(G41*C41)/100 -> 0.23898 | J41: =+(((I41*$I$125)+(F41*(1+$E$125)))*(1+$C$131)) -> 56.426134 | K41: =IF(J41=0,0,J41/C41) -> 56.426134 | M41: 3-1/2-HW | O41: 3139 | Q41: 3073 | R41: =(O41-Q41)/Q41 -> 0.021477384
A42: 3-1/2" HW Unit | B42: 0.2 | C42: 1 | D42: =O41*B42+O41 -> 3766.8 | E42: C | F42: =+(D42*C42)/100 -> 37.668 | G42: 27.719 | H42: C | I42: =+(G42*C42)/100 -> 0.27719 | J42: =+(((I42*$I$125)+(F42*(1+$E$125)))*(1+$C$131)) -> 68.69359 | K42: =IF(J42=0,0,J42/C42) -> 68.69359 | M42: 3-1/2-IMC | O42: 2448 | Q42: 2397 | R42: =(O42-Q42)/Q42 -> 0.021276596 | S42: BX Cable labor rate / ft
A43: 4" HW Unit | B43: 0.2 | C43: 1 | D43: =O45*B43+O45 -> 3981.6 | E43: C | F43: =+(D43*C43)/100 -> 39.816 | G43: 32.883 | H43: C | I43: =+(G43*C43)/100 -> 0.32883 | J43: =+(((I43*$I$125)+(F43*(1+$E$125)))*(1+$C$131)) -> 76.12248 | K43: =IF(J43=0,0,J43/C43) -> 76.12248 | M43: 3-1/2-PVC40 | O43: 785 | Q43: 785 | R43: =(O43-Q43)/Q43 -> 0 | S43: 14/2: .012 .015 .018
J44: =+(((I44*$I$125)+(F44*(1+$E$125)))*(1+$C$131)) -> 0 | K44: =IF(J44=0,0,J44/C44) -> 0 | M44: 4-EMT | O44: 1351 | Q44: 1322 | R44: =(O44-Q44)/Q44 -> 0.02193646 | S44: 12/2: .015 .019 .023
A45: IMC Unit | J45: =+(((I45*$I$125)+(F45*(1+$E$125)))*(1+$C$131)) -> 0 | K45: =IF(J45=0,0,J45/C45) -> 0 | M45: 4-HW | O45: 3318 | Q45: 3248 | R45: =(O45-Q45)/Q45 -> 0.021551724 | S45: 10/2: .018 .023 .027
A46: 1/2" IMC Unit | B46: 0.5 | C46: 1 | D46: =O10*B46+O10 -> 304.5 | E46: C | F46: =+(D46*C46)/100 -> 3.045 | G46: 7.524 | H46: C | I46: =+(G46*C46)/100 -> 0.07524 | J46: =+(((I46*$I$125)+(F46*(1+$E$125)))*(1+$C$131)) -> 10.730633 | K46: =IF(J46=0,0,J46/C46) -> 10.730633 | M46: 4-IMC | O46: 2751 | Q46: 2693 | R46: =(O46-Q46)/Q46 -> 0.021537319 | S46: 14/3: .018 .023 .027
A47: 3/4" IMC Unit | B47: 0.45 | C47: 1 | D47: =O14*B47+O14 -> 346.55 | E47: C | F47: =+(D47*C47)/100 -> 3.4655 | G47: 8.413 | H47: C | I47: =+(G47*C47)/100 -> 0.08413 | J47: =+(((I47*$I$125)+(F47*(1+$E$125)))*(1+$C$131)) -> 12.065454 | K47: =IF(J47=0,0,J47/C47) -> 12.065454 | M47: 4-PVC40 | O47: 856 | Q47: 856 | R47: =(O47-Q47)/Q47 -> 0 | S47: 12/3: .021 .026 .032
A48: 1" IMC Unit | B48: 0.4 | C48: 1 | D48: =O18*B48+O18 -> 513.8 | E48: C | F48: =+(D48*C48)/100 -> 5.138 | G48: 9.173 | H48: C | I48: =+(G48*C48)/100 -> 0.09173 | J48: =+(((I48*$I$125)+(F48*(1+$E$125)))*(1+$C$131)) -> 14.654185 | K48: =IF(J48=0,0,J48/C48) -> 14.654185 | M48: 5-PVC40 | O48: 1204 | Q48: 1204 | R48: =(O48-Q48)/Q48 -> 0 | S48: 10/3: .024 .030 .036
A49: 1-1/4" IMC Unit | B49: 0.4 | C49: 1 | D49: =O22*B49+O22 -> 721 | E49: C | F49: =+(D49*C49)/100 -> 7.21 | G49: 9.702 | H49: C | I49: =+(G49*C49)/100 -> 0.09702 | J49: =+(((I49*$I$125)+(F49*(1+$E$125)))*(1+$C$131)) -> 17.456985 | K49: =IF(J49=0,0,J49/C49) -> 17.456985 | M49: 6-PVC40 | O49: 1579 | Q49: 1579 | R49: =(O49-Q49)/Q49 -> 0
A50: 1-1/2" IMC Unit | B50: 0.4 | C50: 1 | D50: =O26*B50+O26 -> 897.4 | E50: C | F50: =+(D50*C50)/100 -> 8.974 | G50: 11.157 | H50: C | I50: =+(G50*C50)/100 -> 0.11157 | J50: =+(((I50*$I$125)+(F50*(1+$E$125)))*(1+$C$131)) -> 20.827695 | K50: =IF(J50=0,0,J50/C50) -> 20.827695 | M50: 5-HW | O50: 6242 | Q50: 6111 | R50: =(O50-Q50)/Q50 -> 0.021436753
A51: 2" IMC Unit | B51: 0.35 | C51: 1 | D51: =O30*B51+O30 -> 1082.7 | E51: C | F51: =+(D51*C51)/100 -> 10.827 | G51: 13.298 | H51: C | I51: =+(G51*C51)/100 -> 0.13298 | J51: =+(((I51*$I$125)+(F51*(1+$E$125)))*(1+$C$131)) -> 24.968807 | K51: =IF(J51=0,0,J51/C51) -> 24.968807 | M51: 6-HW | O51: 8142 | Q51: 7971 | R51: =(O51-Q51)/Q51 -> 0.021452766
A52: 2-1/2" IMC Unit | B52: 0.3 | C52: 1 | D52: =O34*B52+O34 -> 2068.3 | E52: C | F52: =+(D52*C52)/100 -> 20.683 | G52: 14.798 | H52: C | I52: =+(G52*C52)/100 -> 0.14798 | J52: =+(((I52*$I$125)+(F52*(1+$E$125)))*(1+$C$131)) -> 37.305048 | K52: =IF(J52=0,0,J52/C52) -> 37.305048
A53: 3" IMC Unit | B53: 0.25 | C53: 1 | D53: =O38*B53+O38 -> 2602.5 | E53: C | F53: =+(D53*C53)/100 -> 26.025 | G53: 17.748 | H53: C | I53: =+(G53*C53)/100 -> 0.17748 | J53: =+(((I53*$I$125)+(F53*(1+$E$125)))*(1+$C$131)) -> 46.085603 | K53: =IF(J53=0,0,J53/C53) -> 46.085603
A54: 3-1/2" IMC Unit | B54: 0.2 | C54: 1 | D54: =O42*B54+O42 -> 2937.6 | E54: C | F54: =+(D54*C54)/100 -> 29.376 | G54: 21.418 | H54: C | I54: =+(G54*C54)/100 -> 0.21418 | J54: =+(((I54*$I$125)+(F54*(1+$E$125)))*(1+$C$131)) -> 53.37668 | K54: =IF(J54=0,0,J54/C54) -> 53.37668
A55: 4" IMC Unit | B55: 0.2 | C55: 1 | D55: =O46*B55+O46 -> 3301.2 | E55: C | F55: =+(D55*C55)/100 -> 33.012 | G55: 25.133 | H55: C | I55: =+(G55*C55)/100 -> 0.25133 | J55: =+(((I55*$I$125)+(F55*(1+$E$125)))*(1+$C$131)) -> 61.02607 | K55: =IF(J55=0,0,J55/C55) -> 61.02607
J56: =+(((I56*$I$125)+(F56*(1+$E$125)))*(1+$C$131)) -> 0 | K56: =IF(J56=0,0,J56/C56) -> 0
A57: PVC Unit | J57: =+(((I57*$I$125)+(F57*(1+$E$125)))*(1+$C$131)) -> 0 | K57: =IF(J57=0,0,J57/C57) -> 0
A58: 1/2" PVC Slab Unit | B58: 0.5 | C58: 1 | D58: =O11*B58+O11 -> 133.5 | E58: C | F58: =+(D58*C58)/100 -> 1.335 | G58: 4.058 | H58: C | I58: =+(G58*C58)/100 -> 0.04058 | J58: =+(((I58*$I$125)+(F58*(1+$E$125)))*(1+$C$131)) -> 5.4486775 | K58: =IF(J58=0,0,J58/C58) -> 5.4486775
A59: 3/4" PVC Slab Unit | B59: 0.45 | C59: 1 | D59: =O15*B59+O15 -> 156.6 | E59: C | F59: =+(D59*C59)/100 -> 1.566 | G59: 4.635 | H59: C | I59: =+(G59*C59)/100 -> 0.04635 | J59: =+(((I59*$I$125)+(F59*(1+$E$125)))*(1+$C$131)) -> 6.268815 | K59: =IF(J59=0,0,J59/C59) -> 6.268815
A60: 1" PVC Slab Unit | B60: 0.4 | C60: 1 | D60: =O19*B60+O19 -> 229.6 | E60: C | F60: =+(D60*C60)/100 -> 2.296 | G60: 5.265 | H60: C | I60: =+(G60*C60)/100 -> 0.05265 | J60: =+(((I60*$I$125)+(F60*(1+$E$125)))*(1+$C$131)) -> 7.69104 | K60: =IF(J60=0,0,J60/C60) -> 7.69104
A61: 1-1/4" PVC Slab Unit | B61: 0.4 | C61: 1 | D61: =O23*B61+O23 -> 310.8 | E61: C | F61: =+(D61*C61)/100 -> 3.108 | G61: 5.17 | H61: C | I61: =+(G61*C61)/100 -> 0.0517 | J61: =+(((I61*$I$125)+(F61*(1+$E$125)))*(1+$C$131)) -> 8.49317 | K61: =IF(J61=0,0,J61/C61) -> 8.49317
A62: 1-1/2" PVC Slab Unit | B62: 0.4 | C62: 1 | D62: =O27*B62+O27 -> 359.8 | E62: C | F62: =+(D62*C62)/100 -> 3.598 | G62: 5.86 | H62: C | I62: =+(G62*C62)/100 -> 0.0586 | J62: =+(((I62*$I$125)+(F62*(1+$E$125)))*(1+$C$131)) -> 9.709595 | K62: =IF(J62=0,0,J62/C62) -> 9.709595
A63: 2" PVC Slab Unit | B63: 0.35 | C63: 1 | D63: =O31*B63+O31 -> 440.1 | E63: C | F63: =+(D63*C63)/100 -> 4.401 | G63: 6.645 | H63: C | I63: =+(G63*C63)/100 -> 0.06645 | J63: =+(((I63*$I$125)+(F63*(1+$E$125)))*(1+$C$131)) -> 11.364202 | K63: =IF(J63=0,0,J63/C63) -> 11.364202
A64: 2-1/2" PVC Slab Unit | B64: 0.3 | C64: 1 | D64: =O35*B64+O35 -> 657.8 | E64: C | F64: =+(D64*C64)/100 -> 6.578 | G64: 7.565 | H64: C | I64: =+(G64*C64)/100 -> 0.07565 | J64: =+(((I64*$I$125)+(F64*(1+$E$125)))*(1+$C$131)) -> 14.665945 | K64: =IF(J64=0,0,J64/C64) -> 14.665945
A65: 3" PVC Slab Unit | B65: 0.25 | C65: 1 | D65: =O39*B65+O39 -> 768.75 | E65: C | F65: =+(D65*C65)/100 -> 7.6875 | G65: 8.58 | H65: C | I65: =+(G65*C65)/100 -> 0.0858 | J65: =+(((I65*$I$125)+(F65*(1+$E$125)))*(1+$C$131)) -> 16.883869 | K65: =IF(J65=0,0,J65/C65) -> 16.883869
A66: 3-1/2" PVC Slab Unit | B66: 0.2 | C66: 1 | D66: =O43*B66+O43 -> 942 | E66: C | F66: =+(D66*C66)/100 -> 9.42 | G66: 9.26 | H66: C | I66: =+(G66*C66)/100 -> 0.0926 | J66: =+(((I66*$I$125)+(F66*(1+$E$125)))*(1+$C$131)) -> 19.46035 | K66: =IF(J66=0,0,J66/C66) -> 19.46035
A67: 4" PVC Slab Unit | B67: 0.2 | C67: 1 | D67: =O47*B67+O47 -> 1027.2 | E67: C | F67: =+(D67*C67)/100 -> 10.272 | G67: 11.63 | H67: C | I67: =+(G67*C67)/100 -> 0.1163 | J67: =+(((I67*$I$125)+(F67*(1+$E$125)))*(1+$C$131)) -> 22.72228 | K67: =IF(J67=0,0,J67/C67) -> 22.72228
A68: 5" PVC Slab Unit | B68: 0.2 | C68: 1 | D68: =O48*B68+O48 -> 1444.8 | E68: C | F68: =+(D68*C68)/100 -> 14.448 | G68: 13.47 | H68: C | I68: =+(G68*C68)/100 -> 0.1347 | J68: =+(((I68*$I$125)+(F68*(1+$E$125)))*(1+$C$131)) -> 29.12952 | K68: =IF(J68=0,0,J68/C68) -> 29.12952
A70: PVC/GRC Unit | J70: =+(((I70*$I$125)+(F70*(1+$E$125)))*(1+$C$131)) -> 0 | K70: =IF(J70=0,0,J70/C70) -> 0
A71: 1/2" PVC/GRC Unit Assy | C71: 1 | D71: 8.95 | E71: E | F71: =+D71*C71 -> 8.95 | G71: 12.094 | H71: C | I71: =+(G71*C71)/100 -> 0.12094 | J71: =+(((I71*$I$125)+(F71*(1+$E$125)))*(1+$C$131)) -> 21.719495 | K71: =IF(J71=0,0,J71/C71) -> 21.719495
A72: 3/4" PVC/GRC Unit Assy | C72: 1 | D72: 10.02 | E72: E | F72: =+D72*C72 -> 10.02 | G72: 13.774 | H72: C | I72: =+(G72*C72)/100 -> 0.13774 | J72: =+(((I72*$I$125)+(F72*(1+$E$125)))*(1+$C$131)) -> 24.54557 | K72: =IF(J72=0,0,J72/C72) -> 24.54557
A73: 1" PVC/GRC Unit Assy | C73: 1 | D73: 11.03 | E73: E | F73: =+D73*C73 -> 11.03 | G73: 13.16 | H73: C | I73: =+(G73*C73)/100 -> 0.1316 | J73: =+(((I73*$I$125)+(F73*(1+$E$125)))*(1+$C$131)) -> 25.057375 | K73: =IF(J73=0,0,J73/C73) -> 25.057375
A74: 1-1/4" PVC/GRC Unit Assy | C74: 1 | D74: 13.26 | E74: E | F74: =+D74*C74 -> 13.26 | G74: 14.84 | H74: C | I74: =+(G74*C74)/100 -> 0.1484 | J74: =+(((I74*$I$125)+(F74*(1+$E$125)))*(1+$C$131)) -> 29.16235 | K74: =IF(J74=0,0,J74/C74) -> 29.16235
A75: 1-1/2" PVC/GRC Unit Assy | C75: 1 | D75: 16.24 | E75: E | F75: =+D75*C75 -> 16.24 | G75: 17.747 | H75: C | I75: =+(G75*C75)/100 -> 0.17747 | J75: =+(((I75*$I$125)+(F75*(1+$E$125)))*(1+$C$131)) -> 35.29666 | K75: =IF(J75=0,0,J75/C75) -> 35.29666
A76: 2" PVC/GRC Unit Assy | C76: 1 | D76: 22.55 | E76: E | F76: =+D76*C76 -> 22.55 | G76: 20.948 | H76: C | I76: =+(G76*C76)/100 -> 0.20948 | J76: =+(((I76*$I$125)+(F76*(1+$E$125)))*(1+$C$131)) -> 45.390415 | K76: =IF(J76=0,0,J76/C76) -> 45.390415
A77: 2-1/2" PVC/GRC Unit Assy | C77: 1 | D77: 32.47 | E77: E | F77: =+D77*C77 -> 32.47 | G77: 22.702 | H77: C | I77: =+(G77*C77)/100 -> 0.22702 | J77: =+(((I77*$I$125)+(F77*(1+$E$125)))*(1+$C$131)) -> 58.046135 | K77: =IF(J77=0,0,J77/C77) -> 58.046135
A78: 3" PVC/GRC Unit Assy | C78: 1 | D78: 42.82 | E78: E | F78: =+D78*C78 -> 42.82 | G78: 26.433 | H78: C | I78: =+(G78*C78)/100 -> 0.26433 | J78: =+(((I78*$I$125)+(F78*(1+$E$125)))*(1+$C$131)) -> 73.11339 | K78: =IF(J78=0,0,J78/C78) -> 73.11339
A79: 3-1/2" PVC/GRC Unit Assy | C79: 1 | D79: 62.38 | E79: E | F79: =+D79*C79 -> 62.38 | G79: 29.593 | H79: C | I79: =+(G79*C79)/100 -> 0.29593 | J79: =+(((I79*$I$125)+(F79*(1+$E$125)))*(1+$C$131)) -> 97.77509 | K79: =IF(J79=0,0,J79/C79) -> 97.77509
A80: 4" PVC/GRC Unit Assy | C80: 1 | D80: 70.64 | E80: E | F80: =+D80*C80 -> 70.64 | G80: 36.198 | H80: C | I80: =+(G80*C80)/100 -> 0.36198 | J80: =+(((I80*$I$125)+(F80*(1+$E$125)))*(1+$C$131)) -> 113.35464 | K80: =IF(J80=0,0,J80/C80) -> 113.35464
A82: THHN WIRE | B82: MARKET PRICE | Q82: Previous
A83: ﻿#12 Thhn Stranded | B83: 189 | C83: 1 | D83: =B83*0.15+B83 -> 217.35 | E83: M | F83: =+(D83*C83)/1000 -> 0.21735 | G83: 5.5 | H83: M | I83: =+(G83*C83)/1000 -> 0.0055 | J83: =+(((I83*$I$125)+(F83*(1+$E$125)))*(1+$C$131)) -> 0.77862837 | K83: =IF(J83=0,0,J83/C83) -> 0.77862837 | L83: 0.39 | Q83: 193 | R83: =(B83-Q83)/Q83 -> -0.020725389
A84: #10 Thhn Stranded | B84: 288 | C84: 1 | D84: =B84*0.15+B84 -> 331.2 | E84: M | F84: =+(D84*C84)/1000 -> 0.3312 | G84: 6 | H84: M | I84: =+(G84*C84)/1000 -> 0.006 | J84: =+(((I84*$I$125)+(F84*(1+$E$125)))*(1+$C$131)) -> 0.953148 | K84: =IF(J84=0,0,J84/C84) -> 0.953148 | L84: 0.6 | Q84: 296 | R84: =(B84-Q84)/Q84 -> -0.027027027
A85: #8 Thhn Stranded | B85: 540 | C85: 1 | D85: =B85*0.1+B85 -> 594 | E85: M | F85: =+(D85*C85)/1000 -> 0.594 | G85: 6.25 | H85: M | I85: =+(G85*C85)/1000 -> 0.00625 | J85: =+(((I85*$I$125)+(F85*(1+$E$125)))*(1+$C$131)) -> 1.267385 | K85: =IF(J85=0,0,J85/C85) -> 1.267385 | L85: 0.85 | Q85: 539 | R85: =(B85-Q85)/Q85 -> 0.0018552876
A86: #6 Thhn Stranded | B86: 830 | C86: 1 | D86: =B86*0.1+B86 -> 913 | E86: M | F86: =+(D86*C86)/1000 -> 0.913 | G86: 7 | H86: M | I86: =+(G86*C86)/1000 -> 0.007 | J86: =+(((I86*$I$125)+(F86*(1+$E$125)))*(1+$C$131)) -> 1.6925825 | K86: =IF(J86=0,0,J86/C86) -> 1.6925825 | L86: 1.04 | Q86: 829 | R86: =(B86-Q86)/Q86 -> 0.0012062726
A87: #4 Thhn Stranded | B87: 1270 | C87: 1 | D87: =B87*0.1+B87 -> 1397 | E87: M | F87: =+(D87*C87)/1000 -> 1.397 | G87: 8.5 | H87: M | I87: =+(G87*C87)/1000 -> 0.0085 | J87: =+(((I87*$I$125)+(F87*(1+$E$125)))*(1+$C$131)) -> 2.3731925 | K87: =IF(J87=0,0,J87/C87) -> 2.3731925 | L87: 1.33 | Q87: 1268 | R87: =(B87-Q87)/Q87 -> 0.0015772871
A88: #3 Thhn Stranded | B88: 1602 | C88: 1 | D88: =B88*0.05+B88 -> 1682.1 | E88: M | F88: =+(D88*C88)/1000 -> 1.6821 | G88: 9 | H88: M | I88: =+(G88*C88)/1000 -> 0.009 | J88: =+(((I88*$I$125)+(F88*(1+$E$125)))*(1+$C$131)) -> 2.7365153 | K88: =IF(J88=0,0,J88/C88) -> 2.7365153 | L88: 1.51 | Q88: 1599 | R88: =(B88-Q88)/Q88 -> 0.0018761726
A89: #2 Thhn Stranded | B89: 2005 | C89: 1 | D89: =B89*0.05+B89 -> 2105.25 | E89: M | F89: =+(D89*C89)/1000 -> 2.10525 | G89: 10 | H89: M | I89: =+(G89*C89)/1000 -> 0.01 | J89: =+(((I89*$I$125)+(F89*(1+$E$125)))*(1+$C$131)) -> 3.3010381 | K89: =IF(J89=0,0,J89/C89) -> 3.3010381 | L89: 1.745 | Q89: 2002 | R89: =(B89-Q89)/Q89 -> 0.0014985015
A90: #1 Thhn Stranded | B90: 2242 | C90: 1 | D90: =B90*0.05+B90 -> 2354.1 | E90: M | F90: =+(D90*C90)/1000 -> 2.3541 | G90: 11 | H90: M | I90: =+(G90*C90)/1000 -> 0.011 | J90: =+(((I90*$I$125)+(F90*(1+$E$125)))*(1+$C$131)) -> 3.6733952 | K90: =IF(J90=0,0,J90/C90) -> 3.6733952 | L90: 2.13 | Q90: 2238 | R90: =(B90-Q90)/Q90 -> 0.0017873101
A91: #1/0 Thhn Stranded | B91: 2745 | C91: 1 | D91: =B91*0.05+B91 -> 2882.25 | E91: M | F91: =+(D91*C91)/1000 -> 2.88225 | G91: 13 | H91: M | I91: =+(G91*C91)/1000 -> 0.013 | J91: =+(((I91*$I$125)+(F91*(1+$E$125)))*(1+$C$131)) -> 4.4516806 | K91: =IF(J91=0,0,J91/C91) -> 4.4516806 | L91: 2.6 | Q91: 2740 | R91: =(B91-Q91)/Q91 -> 0.0018248175
A92: #2/0 Thhn Stranded | B92: 3381 | C92: 1 | D92: =B92*0.05+B92 -> 3550.05 | E92: M | F92: =+(D92*C92)/1000 -> 3.55005 | G92: 15 | H92: M | I92: =+(G92*C92)/1000 -> 0.015 | J92: =+(((I92*$I$125)+(F92*(1+$E$125)))*(1+$C$131)) -> 5.3839301 | K92: =IF(J92=0,0,J92/C92) -> 5.3839301 | L92: 3.05 | Q92: 3376 | R92: =(B92-Q92)/Q92 -> 0.0014810427
A93: #3/0 Thhn Stranded | B93: 4267 | C93: 1 | D93: =B93*0.05+B93 -> 4480.35 | E93: M | F93: =+(D93*C93)/1000 -> 4.48035 | G93: 17 | H93: M | I93: =+(G93*C93)/1000 -> 0.017 | J93: =+(((I93*$I$125)+(F93*(1+$E$125)))*(1+$C$131)) -> 6.6055859 | K93: =IF(J93=0,0,J93/C93) -> 6.6055859 | L93: 3.7 | Q93: 4260 | R93: =(B93-Q93)/Q93 -> 0.0016431925
A94: #4/0 Thhn Stranded | B94: 5326 | C94: 1 | D94: =B94*0.05+B94 -> 5592.3 | E94: M | F94: =+(D94*C94)/1000 -> 5.5923 | G94: 19 | H94: M | I94: =+(G94*C94)/1000 -> 0.019 | J94: =+(((I94*$I$125)+(F94*(1+$E$125)))*(1+$C$131)) -> 8.0275107 | K94: =IF(J94=0,0,J94/C94) -> 8.0275107 | L94: 4.37 | Q94: 5318 | R94: =(B94-Q94)/Q94 -> 0.0015043249
A95: #250 MCM Thhn Wire | B95: 6172 | C95: 1 | D95: =B95*0.05+B95 -> 6480.6 | E95: M | F95: =+(D95*C95)/1000 -> 6.4806 | G95: 22 | H95: M | I95: =+(G95*C95)/1000 -> 0.022 | J95: =+(((I95*$I$125)+(F95*(1+$E$125)))*(1+$C$131)) -> 9.3008615 | K95: =IF(J95=0,0,J95/C95) -> 9.3008615 | L95: 5.11 | Q95: 6162 | R95: =(B95-Q95)/Q95 -> 0.0016228497
A96: #300 MCM Thhn Wire | B96: 7401 | C96: 1 | D96: =B96*0.05+B96 -> 7771.05 | E96: M | F96: =+(D96*C96)/1000 -> 7.77105 | G96: 25.5 | H96: M | I96: =+(G96*C96)/1000 -> 0.0255 | J96: =+(((I96*$I$125)+(F96*(1+$E$125)))*(1+$C$131)) -> 11.066583 | K96: =IF(J96=0,0,J96/C96) -> 11.066583 | L96: 5.83 | Q96: 7389 | R96: =(B96-Q96)/Q96 -> 0.0016240357
A97: #350 MCM Thhn Wire | B97: 8666 | C97: 1 | D97: =B97*0.05+B97 -> 9099.3 | E97: M | F97: =+(D97*C97)/1000 -> 9.0993 | G97: 27 | H97: M | I97: =+(G97*C97)/1000 -> 0.027 | J97: =+(((I97*$I$125)+(F97*(1+$E$125)))*(1+$C$131)) -> 12.677978 | K97: =IF(J97=0,0,J97/C97) -> 12.677978 | L97: 6.68 | Q97: 8652 | R97: =(B97-Q97)/Q97 -> 0.001618123
A98: #400 MCM Thhn Wire | B98: 9858 | C98: 1 | D98: =B98*0.05+B98 -> 10350.9 | E98: M | F98: =+(D98*C98)/1000 -> 10.3509 | G98: 29 | H98: M | I98: =+(G98*C98)/1000 -> 0.029 | J98: =+(((I98*$I$125)+(F98*(1+$E$125)))*(1+$C$131)) -> 14.253867 | K98: =IF(J98=0,0,J98/C98) -> 14.253867 | L98: 7.49 | Q98: 9842 | R98: =(B98-Q98)/Q98 -> 0.0016256858
A99: #500 MCM Thhn Wire | B99: 12191 | C99: 1 | D99: =B99*0.05+B99 -> 12800.55 | E99: M | F99: =+(D99*C99)/1000 -> 12.80055 | G99: 33 | H99: M | I99: =+(G99*C99)/1000 -> 0.033 | J99: =+(((I99*$I$125)+(F99*(1+$E$125)))*(1+$C$131)) -> 17.346606 | K99: =IF(J99=0,0,J99/C99) -> 17.346606 | L99: 8.52 | Q99: 12436 | R99: =(B99-Q99)/Q99 -> -0.019700868
A100: #600 MCM Thhn Wire | B100: 15192 | C100: 1 | D100: =B100*0.05+B100 -> 15951.6 | E100: M | F100: =+(D100*C100)/1000 -> 15.9516 | G100: 37 | H100: M | I100: =+(G100*C100)/1000 -> 0.037 | J100: =+(((I100*$I$125)+(F100*(1+$E$125)))*(1+$C$131)) -> 21.212639 | K100: =IF(J100=0,0,J100/C100) -> 21.212639 | L100: 11.24 | Q100: 15496 | R100: =(B100-Q100)/Q100 -> -0.019617966
A101: #750 MCM Thhn Wire | B101: 26237 | C101: 1 | D101: =B101*0.1+B101 -> 28860.7 | E101: M | F101: =+(D101*C101)/1000 -> 28.8607 | G101: 42 | H101: M | I101: =+(G101*C101)/1000 -> 0.042 | J101: =+(((I101*$I$125)+(F101*(1+$E$125)))*(1+$C$131)) -> 35.934922 | K101: =IF(J101=0,0,J101/C101) -> 35.934922 | L101: 17.99 | Q101: 26194 | R101: =(B101-Q101)/Q101 -> 0.0016415973
A107: ALUM WIRE | B107: MARKET PRICE | Q107: Previous
...

Sheet Copy
A1: Project | D1: Project# | F1: DATE: | G1: Prepared BY | N1: 10 | O1: 1/2" | P1: 83 | Q1: ﻿#12 Thhn Stranded | T1: 108 | U1: #1 Thhn Stranded
A2: Job Name | D2: KM05 | F2: Todays Date | G2: KM | N2: 11 | O2: 3/4" | P2: 84 | Q2: #10 Thhn Stranded | T2: 109 | U2: #1/0 Thhn Stranded
A3: Job Location | N3: 12 | O3: 1" | P3: 85 | Q3: #8 Thhn Stranded | T3: 110 | U3: #2/0 Thhn Stranded
A4: G.C. | N4: 13 | O4: 1-1/4" | P4: 86 | Q4: #6 Thhn Stranded | T4: 111 | U4: #3/0 Thhn Stranded
A5: Contact Name | N5: 14 | O5: 1-1/2" | P5: 87 | Q5: #4 Thhn Stranded | T5: 112 | U5: #4/0 Thhn Stranded
A6: Telephone - Fax | N6: 15 | O6: 2" | P6: 88 | Q6: #3 Thhn Stranded | T6: 113 | U6: #250 MCM Thhn Wire
N7: 16 | O7: 2-1/2" | P7: 89 | Q7: #2 Thhn Stranded | T7: 114 | U7: #300 MCM Thhn Wire
A8: MATERIAL | C8: QTY | D8: MAT UNIT | E8: per | F8: EXTENSION | G8: LBR UNIT | H8: per | I8: EXTENSION | J8: TOTAL | K8: $$/QTY | N8: 17 | O8: 3" | P8: 90 | Q8: #1 Thhn Stranded | T8: 115 | U8: #350 MCM Thhn Wire
N9: 18 | O9: 3-1/2" | P9: 91 | Q9: #1/0 Thhn Stranded | T9: 116 | U9: #400 MCM Thhn Wire
N10: 19 | O10: 4" | P10: 92 | Q10: #2/0 Thhn Stranded | T10: 117 | U10: #500 MCM Thhn Wire
A11: TEMP POWER | B11: =SUM(J12:J14) -> 0 | P11: 93 | Q11: #3/0 Thhn Stranded | T11: 118 | U11: #600 MCM Thhn Wire
A12: Temp power from ComEd permanent power | D12: =F327/100 -> 8285.2 | E12: Lot | F12: =+D12*C12 -> 0 | G12: =F327/10000 -> 82.852 | H12: Lot | I12: =+G12*C12 -> 0 | J12: =+(((I12*$I$324)+(F12*(1+$E$324)))*(1+$C$330)) -> 0 | K12: =IF(J12=0,0,J12/C12) -> 0 | P12: 94 | Q12: #4/0 Thhn Stranded | T12: 119 | U12: #750 MCM Thhn Wire
A13: Hook up of construction trailer | D13: 1500 | E13: Lot | F13: =+D13*C13 -> 0 | G13: 30 | H13: Lot | I13: =+G13*C13 -> 0 | J13: =+(((I13*$I$324)+(F13*(1+$E$324)))*(1+$C$330)) -> 0 | K13: =IF(J13=0,0,J13/C13) -> 0 | P13: 95 | Q13: #250 MCM Thhn Wire | T13: 120 | U13: #900 MCM Thhn Wire
P14: 96 | Q14: #300 MCM Thhn Wire
A15: ELECTRICAL SERVICE & DISTRIBUTION | B15: =SUM(J16:J158) -> 600.58381 | K15: =IF(J15=0,0,J15/C15) -> 0 | P15: 97 | Q15: #350 MCM Thhn Wire
A16: ComEd pad | D16: 2000 | E16: E | F16: =+D16*C16 -> 0 | G16: 10 | H16: E | I16: =+G16*C16 -> 0 | J16: =+(((I16*$I$324)+(F16*(1+$E$324)))*(1+$C$330)) -> 0 | K16: =IF(J16=0,0,J16/C16) -> 0 | P16: 98 | Q16: #400 MCM Thhn Wire
A17: Rework existing panel for new loads | D17: 400 | E17: E | F17: =+D17*C17 -> 0 | G17: 4 | H17: E | I17: =+G17*C17 -> 0 | J17: =+(((I17*$I$324)+(F17*(1+$E$324)))*(1+$C$330)) -> 0 | K17: =IF(J17=0,0,J17/C17) -> 0 | P17: 99 | Q17: #500 MCM Thhn Wire
A18: 4000A., 277/480V., 3PH. Main switchboard w/ meter | D18: 35000 | E18: E | F18: =+D18*C18 -> 0 | G18: 124 | H18: E | I18: =+G18*C18 -> 0 | J18: =+(((I18*$I$324)+(F18*(1+$E$324)))*(1+$C$330)) -> 0 | K18: =IF(J18=0,0,J18/C18) -> 0 | P18: 100 | Q18: #600 MCM Thhn Wire
B19: CU feed (ft) | D19: =((FEEDERS!$D$100*4)/10+FEEDERS!$D$19)*10 -> 79342.9 | E19: C | F19: =+(D19*C19)/100 -> 0 | G19: =((FEEDERS!$G$100*4)/10+FEEDERS!$G$19)*10 -> 335.75 | H19: C | I19: =+(G19*C19)/100 -> 0 | J19: =+(((I19*$I$324)+(F19*(1+$E$324)))*(1+$C$330)) -> 0 | K19: =IF(J19=0,0,J19/C19) -> 0 | P19: 101 | Q19: #750 MCM Thhn Wire
B20: AL feed (ft) | D20: =((FEEDERS!$D$119*4)/10+FEEDERS!$D$19)*11 -> 34010.79 | E20: C | F20: =+(D20*C20)/100 -> 0 | G20: =((FEEDERS!$G$119*4)/10+FEEDERS!$G$19)*11 -> 347.325 | H20: C | I20: =+(G20*C20)/100 -> 0 | J20: =+(((I20*$I$324)+(F20*(1+$E$324)))*(1+$C$330)) -> 0 | K20: =IF(J20=0,0,J20/C20) -> 0
A21: 3000A., 277/480V., 3PH. Main switchboard w/ meter | D21: 30000 | E21: E | F21: =+D21*C21 -> 0 | G21: 104 | H21: E | I21: =+G21*C21 -> 0 | J21: =+(((I21*$I$324)+(F21*(1+$E$324)))*(1+$C$330)) -> 0 | K21: =IF(J21=0,0,J21/C21) -> 0
B22: CU feed (ft) | D22: =((FEEDERS!$D$99*4)/10+FEEDERS!$D$19)*8 -> 53390.96 | E22: C | F22: =+(D22*C22)/100 -> 0 | G22: =((FEEDERS!$G$99*4)/10+FEEDERS!$G$19)*8 -> 255.8 | H22: C | I22: =+(G22*C22)/100 -> 0 | J22: =+(((I22*$I$324)+(F22*(1+$E$324)))*(1+$C$330)) -> 0 | K22: =IF(J22=0,0,J22/C22) -> 0
B23: AL feed (ft) | D23: =((FEEDERS!$D$119*4)/10+FEEDERS!$D$19)*8 -> 24735.12 | E23: C | F23: =+(D23*C23)/100 -> 0 | G23: =((FEEDERS!$G$119*4)/10+FEEDERS!$G$19)*8 -> 252.6 | H23: C | I23: =+(G23*C23)/100 -> 0 | J23: =+(((I23*$I$324)+(F23*(1+$E$324)))*(1+$C$330)) -> 0 | K23: =IF(J23=0,0,J23/C23) -> 0
A24: 2500A., 277/480V., 3PH. Main switchboard w/ meter | D24: 25000 | E24: E | F24: =+D24*C24 -> 0 | G24: 82 | H24: E | I24: =+G24*C24 -> 0 | J24: =+(((I24*$I$324)+(F24*(1+$E$324)))*(1+$C$330)) -> 0 | K24: =IF(J24=0,0,J24/C24) -> 0
B25: CU feed (ft) | D25: =((FEEDERS!$D$100*4)/10+FEEDERS!$D$19)*6 -> 47605.74 | E25: C | F25: =+(D25*C25)/100 -> 0 | G25: =((FEEDERS!$G$100*4)/10+FEEDERS!$G$19)*6 -> 201.45 | H25: C | I25: =+(G25*C25)/100 -> 0 | J25: =+(((I25*$I$324)+(F25*(1+$E$324)))*(1+$C$330)) -> 0 | K25: =IF(J25=0,0,J25/C25) -> 0
B26: AL feed (ft) | D26: =((FEEDERS!$D$119*4)/10+FEEDERS!$D$19)*7 -> 21643.23 | E26: C | F26: =+(D26*C26)/100 -> 0 | G26: =((FEEDERS!$G$119*4)/10+FEEDERS!$G$19)*7 -> 221.025 | H26: C | I26: =+(G26*C26)/100 -> 0 | J26: =+(((I26*$I$324)+(F26*(1+$E$324)))*(1+$C$330)) -> 0 | K26: =IF(J26=0,0,J26/C26) -> 0 | U26: k
A27: 2000A., 277/480V., 3PH. Main switchboard w/ meter | D27: 23000 | E27: E | F27: =+D27*C27 -> 0 | G27: 66 | H27: E | I27: =+G27*C27 -> 0 | J27: =+(((I27*$I$324)+(F27*(1+$E$324)))*(1+$C$330)) -> 0 | K27: =IF(J27=0,0,J27/C27) -> 0
B28: CU feed (ft) | D28: =((FEEDERS!$D$100*4)/10+FEEDERS!$D$19)*5 -> 39671.45 | E28: C | F28: =+(D28*C28)/100 -> 0 | G28: =((FEEDERS!$G$100*4)/10+FEEDERS!$G$19)*5 -> 167.875 | H28: C | I28: =+(G28*C28)/100 -> 0 | J28: =+(((I28*$I$324)+(F28*(1+$E$324)))*(1+$C$330)) -> 0 | K28: =IF(J28=0,0,J28/C28) -> 0
B29: AL feed (ft) | D29: =((FEEDERS!$D$118*4)/10+FEEDERS!$D$19)*6 -> 16876.86 | E29: C | F29: =+(D29*C29)/100 -> 0 | G29: =((FEEDERS!$G$118*4)/10+FEEDERS!$G$19)*6 -> 182.25 | H29: C | I29: =+(G29*C29)/100 -> 0 | J29: =+(((I29*$I$324)+(F29*(1+$E$324)))*(1+$C$330)) -> 0 | K29: =IF(J29=0,0,J29/C29) -> 0
A30: 1600A., 277/480V., 3PH. Main switchboard w/ meter | D30: 20000 | E30: E | F30: =+D30*C30 -> 0 | G30: 55 | H30: E | I30: =+G30*C30 -> 0 | J30: =+(((I30*$I$324)+(F30*(1+$E$324)))*(1+$C$330)) -> 0 | K30: =IF(J30=0,0,J30/C30) -> 0
B31: CU feed (ft) | D31: =((FEEDERS!$D$100*4)/10+FEEDERS!$D$19)*4 -> 31737.16 | E31: C | F31: =+(D31*C31)/100 -> 0 | G31: =((FEEDERS!$G$100*4)/10+FEEDERS!$G$19)*4 -> 134.3 | H31: C | I31: =+(G31*C31)/100 -> 0 | J31: =+(((I31*$I$324)+(F31*(1+$E$324)))*(1+$C$330)) -> 0 | K31: =IF(J31=0,0,J31/C31) -> 0
B32: AL feed (ft) | D32: =((FEEDERS!$D$118*4)/10+FEEDERS!$D$19)*5 -> 14064.05 | E32: C | F32: =+(D32*C32)/100 -> 0 | G32: =((FEEDERS!$G$118*4)/10+FEEDERS!$G$19)*5 -> 151.875 | H32: C | I32: =+(G32*C32)/100 -> 0 | J32: =+(((I32*$I$324)+(F32*(1+$E$324)))*(1+$C$330)) -> 0 | K32: =IF(J32=0,0,J32/C32) -> 0
A33: 1200A., 277/480V., 3PH. Main distribution board w/ ct/meter | D33: 17000 | E33: E | F33: =+D33*C33 -> 0 | G33: 51 | H33: E | I33: =+G33*C33 -> 0 | J33: =+(((I33*$I$324)+(F33*(1+$E$324)))*(1+$C$330)) -> 0 | K33: =IF(J33=0,0,J33/C33) -> 0
B34: CU feed (ft) | D34: =((FEEDERS!$D$100*4)/10+FEEDERS!$D$19)*3 -> 23802.87 | E34: C | F34: =+(D34*C34)/100 -> 0 | G34: =((FEEDERS!$G$100*4)/10+FEEDERS!$G$19)*3 -> 100.725 | H34: C | I34: =+(G34*C34)/100 -> 0 | J34: =+(((I34*$I$324)+(F34*(1+$E$324)))*(1+$C$330)) -> 0 | K34: =IF(J34=0,0,J34/C34) -> 0
B35: AL feed (ft) | D35: =((FEEDERS!$D$117*4)/10+FEEDERS!$D$17)*4 -> 8974.88 | E35: C | F35: =+(D35*C35)/100 -> 0 | G35: =((FEEDERS!$G$117*4)/10+FEEDERS!$G$17)*4 -> 95.6 | H35: C | I35: =+(G35*C35)/100 -> 0 | J35: =+(((I35*$I$324)+(F35*(1+$E$324)))*(1+$C$330)) -> 0 | K35: =IF(J35=0,0,J35/C35) -> 0
A36: 1000A., 277/480V., 3PH. Main distribution board w/ ct/meter | D36: 15000 | E36: E | F36: =+D36*C36 -> 0 | G36: 41 | H36: E | I36: =+G36*C36 -> 0 | J36: =+(((I36*$I$324)+(F36*(1+$E$324)))*(1+$C$330)) -> 0 | K36: =IF(J36=0,0,J36/C36) -> 0
B37: CU feed (ft) | D37: =((FEEDERS!$D$98*4)/10+FEEDERS!$D$17)*3 -> 16171.08 | E37: C | F37: =+(D37*C37)/100 -> 0 | G37: =((FEEDERS!$G$98*4)/10+FEEDERS!$G$17)*3 -> 75.3 | H37: C | I37: =+(G37*C37)/100 -> 0 | J37: =+(((I37*$I$324)+(F37*(1+$E$324)))*(1+$C$330)) -> 0 | K37: =IF(J37=0,0,J37/C37) -> 0
B38: AL feed (ft) | D38: =((FEEDERS!$D$118*4)/10+FEEDERS!$D$19)*3 -> 8438.43 | E38: C | F38: =+(D38*C38)/100 -> 0 | G38: =((FEEDERS!$G$118*4)/10+FEEDERS!$G$19)*3 -> 91.125 | H38: C | I38: =+(G38*C38)/100 -> 0 | J38: =+(((I38*$I$324)+(F38*(1+$E$324)))*(1+$C$330)) -> 0 | K38: =IF(J38=0,0,J38/C38) -> 0
A39: 800A., 277/480V., 3PH. Distribution board w/ feed | D39: 9000 | E39: E | F39: =+D39*C39 -> 0 | G39: 33 | H39: E | I39: =+G39*C39 -> 0 | J39: =+(((I39*$I$324)+(F39*(1+$E$324)))*(1+$C$330)) -> 0 | K39: =IF(J39=0,0,J39/C39) -> 0
B40: 600 CU feed (ft) | D40: =((FEEDERS!$D$100*4)/10+FEEDERS!$D$19)*2 -> 15868.58 | E40: C | F40: =+(D40*C40)/100 -> 0 | G40: =((FEEDERS!$G$100*4)/10+FEEDERS!$G$19)*2 -> 67.15 | H40: C | I40: =+(G40*C40)/100 -> 0 | J40: =+(((I40*$I$324)+(F40*(1+$E$324)))*(1+$C$330)) -> 0 | K40: =IF(J40=0,0,J40/C40) -> 0
B41: 500 CU feed (ft) | D41: =((FEEDERS!$D$99*4)/10+FEEDERS!$D$19)*2 -> 13347.74 | E41: C | F41: =+(D41*C41)/100 -> 0 | G41: =((FEEDERS!$G$99*4)/10+FEEDERS!$G$19)*2 -> 63.95 | H41: C | I41: =+(G41*C41)/100 -> 0 | J41: =+(((I41*$I$324)+(F41*(1+$E$324)))*(1+$C$330)) -> 0 | K41: =IF(J41=0,0,J41/C41) -> 0
B42: AL feed (ft) | D42: =((FEEDERS!$D$116*4)/10+FEEDERS!$D$16)*3 -> 5775.9 | E42: C | F42: =+(D42*C42)/100 -> 0 | G42: =((FEEDERS!$G$116*4)/10+FEEDERS!$G$16)*3 -> 66.3 | H42: C | I42: =+(G42*C42)/100 -> 0 | J42: =+(((I42*$I$324)+(F42*(1+$E$324)))*(1+$C$330)) -> 0 | K42: =IF(J42=0,0,J42/C42) -> 0
A43: 600A., 277/480V., 3PH. Main distribution board w/ ct/meter | D43: 8000 | E43: E | F43: =+D43*C43 -> 0 | G43: 28 | H43: E | I43: =+G43*C43 -> 0 | J43: =+(((I43*$I$324)+(F43*(1+$E$324)))*(1+$C$330)) -> 0 | K43: =IF(J43=0,0,J43/C43) -> 0
B44: CU feed (ft) | D44: =((FEEDERS!$D$97*4)/10+FEEDERS!$D$17)*2 -> 9779.44 | E44: C | F44: =+(D44*C44)/100 -> 0 | G44: =((FEEDERS!$G$97*4)/10+FEEDERS!$G$17)*2 -> 48.6 | H44: C | I44: =+(G44*C44)/100 -> 0 | J44: =+(((I44*$I$324)+(F44*(1+$E$324)))*(1+$C$330)) -> 0 | K44: =IF(J44=0,0,J44/C44) -> 0
B45: AL feed (ft) | D45: =((FEEDERS!$D$117*4)/10+FEEDERS!$D$17)*2 -> 4487.44 | E45: C | F45: =+(D45*C45)/100 -> 0 | G45: =((FEEDERS!$G$117*4)/10+FEEDERS!$G$17)*2 -> 47.8 | H45: C | I45: =+(G45*C45)/100 -> 0 | J45: =+(((I45*$I$324)+(F45*(1+$E$324)))*(1+$C$330)) -> 0 | K45: =IF(J45=0,0,J45/C45) -> 0
A46: 400A 277/480V., 3Ph, Panelboard w/ feed | D46: 3000 | E46: E | F46: =+D46*C46 -> 0 | G46: 14 | H46: E | I46: =+G46*C46 -> 0 | J46: =+(((I46*$I$324)+(F46*(1+$E$324)))*(1+$C$330)) -> 0 | K46: =IF(J46=0,0,J46/C46) -> 0
B47: 600 CU feed (ft) | D47: =(FEEDERS!$D$100*4)/10+FEEDERS!$D$19 -> 7934.29 | E47: C | F47: =+(D47*C47)/100 -> 0 | G47: =(FEEDERS!$G$100*4)/10+FEEDERS!$G$19 -> 33.575 | H47: C | I47: =+(G47*C47)/100 -> 0 | J47: =+(((I47*$I$324)+(F47*(1+$E$324)))*(1+$C$330)) -> 0 | K47: =IF(J47=0,0,J47/C47) -> 0
B48: 500 CU feed (ft) | D48: =(FEEDERS!$D$99*4)/10+FEEDERS!$D$19 -> 6673.87 | E48: C | F48: =+(D48*C48)/100 -> 0 | G48: =(FEEDERS!$G$99*4)/10+FEEDERS!$G$19 -> 31.975 | H48: C | I48: =+(G48*C48)/100 -> 0 | J48: =+(((I48*$I$324)+(F48*(1+$E$324)))*(1+$C$330)) -> 0 | K48: =IF(J48=0,0,J48/C48) -> 0
B49: 2- 250 AL feed (ft) | D49: =((FEEDERS!$D$113*4)/10+FEEDERS!$D$16)*2 -> 3145.84 | E49: C | F49: =+(D49*C49)/100 -> 0 | G49: =((FEEDERS!$G$113*4)/10+FEEDERS!$G$16)*2 -> 40.2 | H49: C | I49: =+(G49*C49)/100 -> 0 | J49: =+(((I49*$I$324)+(F49*(1+$E$324)))*(1+$C$330)) -> 0 | K49: =IF(J49=0,0,J49/C49) -> 0
B50: 750 AL feed (ft) | D50: =(FEEDERS!$D$119*4)/10+FEEDERS!$D$19 -> 3091.89 | E50: C | F50: =+(D50*C50)/100 -> 0 | G50: =(FEEDERS!$G$119*4)/10+FEEDERS!$G$19 -> 31.575 | H50: C | I50: =+(G50*C50)/100 -> 0 | J50: =+(((I50*$I$324)+(F50*(1+$E$324)))*(1+$C$330)) -> 0 | K50: =IF(J50=0,0,J50/C50) -> 0
A51: 250A 277/480V., 3PH Panelboard w/ feed | D51: 2300 | E51: E | F51: =+D51*C51 -> 0 | G51: 12 | H51: E | I51: =+G51*C51 -> 0 | J51: =+(((I51*$I$324)+(F51*(1+$E$324)))*(1+$C$330)) -> 0 | K51: =IF(J51=0,0,J51/C51) -> 0
B52: CU feed (ft) | D52: =(FEEDERS!$D$95*4)/10+FEEDERS!$D$16 -> 3616.64 | E52: C | F52: =+(D52*C52)/100 -> 0 | G52: =(FEEDERS!$G$95*4)/10+FEEDERS!$G$16 -> 20.9 | H52: C | I52: =+(G52*C52)/100 -> 0 | J52: =+(((I52*$I$324)+(F52*(1+$E$324)))*(1+$C$330)) -> 0 | K52: =IF(J52=0,0,J52/C52) -> 0
B53: AL feed (ft) | D53: =(FEEDERS!$D$115*4)/10+FEEDERS!$D$16 -> 1795.1 | E53: C | F53: =+(D53*C53)/100 -> 0 | G53: =(FEEDERS!$G$115*4)/10+FEEDERS!$G$16 -> 21.3 | H53: C | I53: =+(G53*C53)/100 -> 0 | J53: =+(((I53*$I$324)+(F53*(1+$E$324)))*(1+$C$330)) -> 0 | K53: =IF(J53=0,0,J53/C53) -> 0
A54: 225A 277/480V., 3PH Panelboard w/ feed | D54: 2300 | E54: E | F54: =+D54*C54 -> 0 | G54: 12 | H54: E | I54: =+G54*C54 -> 0 | J54: =+(((I54*$I$324)+(F54*(1+$E$324)))*(1+$C$330)) -> 0 | K54: =IF(J54=0,0,J54/C54) -> 0
B55: CU feed (ft) | D55: =(FEEDERS!$D$94*4)/10+FEEDERS!$D$16 -> 3261.32 | E55: C | F55: =+(D55*C55)/100 -> 0 | G55: =(FEEDERS!$G$94*4)/10+FEEDERS!$G$16 -> 19.7 | H55: C | I55: =+(G55*C55)/100 -> 0 | J55: =+(((I55*$I$324)+(F55*(1+$E$324)))*(1+$C$330)) -> 0 | K55: =IF(J55=0,0,J55/C55) -> 0
B56: AL feed (ft) | D56: =(FEEDERS!$D$114*4)/10+FEEDERS!$D$16 -> 1782.5 | E56: C | F56: =+(D56*C56)/100 -> 0 | G56: =(FEEDERS!$G$114*4)/10+FEEDERS!$G$16 -> 20.5 | H56: C | I56: =+(G56*C56)/100 -> 0 | J56: =+(((I56*$I$324)+(F56*(1+$E$324)))*(1+$C$330)) -> 0 | K56: =IF(J56=0,0,J56/C56) -> 0
A57: 200A 277/480V., 3PH Panelboard w/ feed | D57: 2300 | E57: E | F57: =+D57*C57 -> 0 | G57: 12 | H57: E | I57: =+G57*C57 -> 0 | J57: =+(((I57*$I$324)+(F57*(1+$E$324)))*(1+$C$330)) -> 0 | K57: =IF(J57=0,0,J57/C57) -> 0
B58: CU feed (ft) | D58: =(FEEDERS!$D$93*4)/10+FEEDERS!$D$15 -> 2492.79 | E58: C | F58: =+(D58*C58)/100 -> 0 | G58: =(FEEDERS!$G$93*4)/10+FEEDERS!$G$15 -> 18.013 | H58: C | I58: =+(G58*C58)/100 -> 0 | J58: =+(((I58*$I$324)+(F58*(1+$E$324)))*(1+$C$330)) -> 0 | K58: =IF(J58=0,0,J58/C58) -> 0
B59: AL feed (ft) | D59: =(FEEDERS!$D$113*4)/10+FEEDERS!$D$16 -> 1572.92 | E59: C | F59: =+(D59*C59)/100 -> 0 | G59: =(FEEDERS!$G$113*4)/10+FEEDERS!$G$16 -> 20.1 | H59: C | I59: =+(G59*C59)/100 -> 0 | J59: =+(((I59*$I$324)+(F59*(1+$E$324)))*(1+$C$330)) -> 0 | K59: =IF(J59=0,0,J59/C59) -> 0
A60: 100A 277/480V., 3PH Panelboard w/ feed | D60: 2000 | E60: E | F60: =+D60*C60 -> 0 | G60: 10 | H60: E | I60: =+G60*C60 -> 0 | J60: =+(((I60*$I$324)+(F60*(1+$E$324)))*(1+$C$330)) -> 0 | K60: =IF(J60=0,0,J60/C60) -> 0
B61: CU feed (ft) | D61: =(FEEDERS!$D$88*4)/10+FEEDERS!$D$13 -> 1181.04 | E61: C | F61: =+(D61*C61)/100 -> 0 | G61: =(FEEDERS!$G$88*4)/10+FEEDERS!$G$13 -> 11.782 | H61: C | I61: =+(G61*C61)/100 -> 0 | J61: =+(((I61*$I$324)+(F61*(1+$E$324)))*(1+$C$330)) -> 0 | K61: =IF(J61=0,0,J61/C61) -> 0
B62: AL feed (ft) | D62: =(FEEDERS!$D$108*4)/10+FEEDERS!$D$13 -> 753.9 | E62: C | F62: =+(D62*C62)/100 -> 0 | G62: =(FEEDERS!$G$108*4)/10+FEEDERS!$G$13 -> 12.982 | H62: C | I62: =+(G62*C62)/100 -> 0 | J62: =+(((I62*$I$324)+(F62*(1+$E$324)))*(1+$C$330)) -> 0 | K62: =IF(J62=0,0,J62/C62) -> 0
A63: 400A 120/208V., 3Ph, Panelboard w/ feed | D63: 3000 | E63: E | F63: =+D63*C63 -> 0 | G63: 14 | H63: E | I63: =+G63*C63 -> 0 | J63: =+(((I63*$I$324)+(F63*(1+$E$324)))*(1+$C$330)) -> 0 | K63: =IF(J63=0,0,J63/C63) -> 0
B64: 600 CU feed (ft) | D64: =(FEEDERS!$D$100*4)/10+FEEDERS!$D$19 -> 7934.29 | E64: C | F64: =+(D64*C64)/100 -> 0 | G64: =(FEEDERS!$G$100*4)/10+FEEDERS!$G$19 -> 33.575 | H64: C | I64: =+(G64*C64)/100 -> 0 | J64: =+(((I64*$I$324)+(F64*(1+$E$324)))*(1+$C$330)) -> 0 | K64: =IF(J64=0,0,J64/C64) -> 0
B65: 500 CU feed (ft) | D65: =(FEEDERS!$D$99*4)/10+FEEDERS!$D$19 -> 6673.87 | E65: C | F65: =+(D65*C65)/100 -> 0 | G65: =(FEEDERS!$G$99*4)/10+FEEDERS!$G$19 -> 31.975 | H65: C | I65: =+(G65*C65)/100 -> 0 | J65: =+(((I65*$I$324)+(F65*(1+$E$324)))*(1+$C$330)) -> 0 | K65: =IF(J65=0,0,J65/C65) -> 0
B66: 2- 250 AL feed (ft) | D66: =((FEEDERS!$D$113*4)/10+FEEDERS!$D$16)*2 -> 3145.84 | E66: C | F66: =+(D66*C66)/100 -> 0 | G66: =((FEEDERS!$G$113*4)/10+FEEDERS!$G$16)*2 -> 40.2 | H66: C | I66: =+(G66*C66)/100 -> 0 | J66: =+(((I66*$I$324)+(F66*(1+$E$324)))*(1+$C$330)) -> 0 | K66: =IF(J66=0,0,J66/C66) -> 0
B67: 750 AL feed (ft) | D67: =(FEEDERS!$D$119*4)/10+FEEDERS!$D$19 -> 3091.89 | E67: C | F67: =+(D67*C67)/100 -> 0 | G67: =(FEEDERS!$G$119*4)/10+FEEDERS!$G$19 -> 31.575 | H67: C | I67: =+(G67*C67)/100 -> 0 | J67: =+(((I67*$I$324)+(F67*(1+$E$324)))*(1+$C$330)) -> 0 | K67: =IF(J67=0,0,J67/C67) -> 0
A68: 200A 120/208V., 3PH Panelboard w/ feed | D68: 2300 | E68: E | F68: =+D68*C68 -> 0 | G68: 12 | H68: E | I68: =+G68*C68 -> 0 | J68: =+(((I68*$I$324)+(F68*(1+$E$324)))*(1+$C$330)) -> 0 | K68: =IF(J68=0,0,J68/C68) -> 0
B69: CU feed (ft) | D69: =(FEEDERS!$D$93*4)/10+FEEDERS!$D$15 -> 2492.79 | E69: C | F69: =+(D69*C69)/100 -> 0 | G69: =(FEEDERS!$G$93*4)/10+FEEDERS!$G$15 -> 18.013 | H69: C | I69: =+(G69*C69)/100 -> 0 | J69: =+(((I69*$I$324)+(F69*(1+$E$324)))*(1+$C$330)) -> 0 | K69: =IF(J69=0,0,J69/C69) -> 0
B70: AL feed (ft) | D70: =(FEEDERS!$D$113*4)/10+FEEDERS!$D$16 -> 1572.92 | E70: C | F70: =+(D70*C70)/100 -> 0 | G70: =(FEEDERS!$G$113*4)/10+FEEDERS!$G$16 -> 20.1 | H70: C | I70: =+(G70*C70)/100 -> 0 | J70: =+(((I70*$I$324)+(F70*(1+$E$324)))*(1+$C$330)) -> 0 | K70: =IF(J70=0,0,J70/C70) -> 0
A71: 150A 120/208V., 3PH Panelboard w/ feed | D71: 2000 | E71: E | F71: =+D71*C71 -> 0 | G71: 10 | H71: E | I71: =+G71*C71 -> 0 | J71: =+(((I71*$I$324)+(F71*(1+$E$324)))*(1+$C$330)) -> 0 | K71: =IF(J71=0,0,J71/C71) -> 0
B72: CU feed (ft) | D72: =(FEEDERS!$D$91*4)/10+FEEDERS!$D$14 -> 1774.5 | E72: C | F72: =+(D72*C72)/100 -> 0 | G72: =(FEEDERS!$G$91*4)/10+FEEDERS!$G$14 -> 14.742 | H72: C | I72: =+(G72*C72)/100 -> 0 | J72: =+(((I72*$I$324)+(F72*(1+$E$324)))*(1+$C$330)) -> 0 | K72: =IF(J72=0,0,J72/C72) -> 0
B73: AL feed (ft) | D73: =(FEEDERS!$D$111*4)/10+FEEDERS!$D$15 -> 1105.11 | E73: C | F73: =+(D73*C73)/100 -> 0 | G73: =(FEEDERS!$G$111*4)/10+FEEDERS!$G$15 -> 17.213 | H73: C | I73: =+(G73*C73)/100 -> 0 | J73: =+(((I73*$I$324)+(F73*(1+$E$324)))*(1+$C$330)) -> 0 | K73: =IF(J73=0,0,J73/C73) -> 0
A74: 125A 120/208V., 3PH Panelboard w/ feed | D74: 2000 | E74: E | F74: =+D74*C74 -> 0 | G74: 10 | H74: E | I74: =+G74*C74 -> 0 | J74: =+(((I74*$I$324)+(F74*(1+$E$324)))*(1+$C$330)) -> 0 | K74: =IF(J74=0,0,J74/C74) -> 0
B75: CU feed (ft) | D75: =(FEEDERS!$D$90*4)/10+FEEDERS!$D$13 -> 1449.84 | E75: C | F75: =+(D75*C75)/100 -> 0 | G75: =(FEEDERS!$G$90*4)/10+FEEDERS!$G$13 -> 12.582 | H75: C | I75: =+(G75*C75)/100 -> 0 | J75: =+(((I75*$I$324)+(F75*(1+$E$324)))*(1+$C$330)) -> 0 | K75: =IF(J75=0,0,J75/C75) -> 0
B76: AL feed (ft) | D76: =(FEEDERS!$D$110*4)/10+FEEDERS!$D$14 -> 947.52 | E76: C | F76: =+(D76*C76)/100 -> 0 | G76: =(FEEDERS!$G$110*4)/10+FEEDERS!$G$14 -> 15.142 | H76: C | I76: =+(G76*C76)/100 -> 0 | J76: =+(((I76*$I$324)+(F76*(1+$E$324)))*(1+$C$330)) -> 0 | K76: =IF(J76=0,0,J76/C76) -> 0
A77: 100A 120/208V., 3PH Panelboard w/ feed | D77: 2000 | E77: E | F77: =+D77*C77 -> 0 | G77: 10 | H77: E | I77: =+G77*C77 -> 0 | J77: =+(((I77*$I$324)+(F77*(1+$E$324)))*(1+$C$330)) -> 0 | K77: =IF(J77=0,0,J77/C77) -> 0
B78: CU feed (ft) | D78: =(FEEDERS!$D$88*4)/10+FEEDERS!$D$13 -> 1181.04 | E78: C | F78: =+(D78*C78)/100 -> 0 | G78: =(FEEDERS!$G$88*4)/10+FEEDERS!$G$13 -> 11.782 | H78: C | I78: =+(G78*C78)/100 -> 0 | J78: =+(((I78*$I$324)+(F78*(1+$E$324)))*(1+$C$330)) -> 0 | K78: =IF(J78=0,0,J78/C78) -> 0
B79: AL feed (ft) | D79: =(FEEDERS!$D$108*4)/10+FEEDERS!$D$13 -> 753.9 | E79: C | F79: =+(D79*C79)/100 -> 0 | G79: =(FEEDERS!$G$108*4)/10+FEEDERS!$G$13 -> 12.982 | H79: C | I79: =+(G79*C79)/100 -> 0 | J79: =+(((I79*$I$324)+(F79*(1+$E$324)))*(1+$C$330)) -> 0 | K79: =IF(J79=0,0,J79/C79) -> 0
A80: 300 KVA transformer | D80: 8000 | E80: E | F80: =+D80*C80 -> 0 | G80: 24 | H80: E | I80: =+G80*C80 -> 0 | J80: =+(((I80*$I$324)+(F80*(1+$E$324)))*(1+$C$330)) -> 0 | K80: =IF(J80=0,0,J80/C80) -> 0
A81: 225 KVA transformer | D81: 6500 | E81: E | F81: =+D81*C81 -> 0 | G81: 24 | H81: E | I81: =+G81*C81 -> 0 | J81: =+(((I81*$I$324)+(F81*(1+$E$324)))*(1+$C$330)) -> 0 | K81: =IF(J81=0,0,J81/C81) -> 0
B82: 600 CU feed (ft) | D82: =(FEEDERS!$D$100*4)/10+FEEDERS!$D$19 -> 7934.29 | E82: C | F82: =+(D82*C82)/100 -> 0 | G82: =(FEEDERS!$G$100*4)/10+FEEDERS!$G$19 -> 33.575 | H82: C | I82: =+(G82*C82)/100 -> 0 | J82: =+(((I82*$I$324)+(F82*(1+$E$324)))*(1+$C$330)) -> 0 | K82: =IF(J82=0,0,J82/C82) -> 0
B83: 500 CU feed (ft) | D83: =(FEEDERS!$D$99*4)/10+FEEDERS!$D$19 -> 6673.87 | E83: C | F83: =+(D83*C83)/100 -> 0 | G83: =(FEEDERS!$G$99*4)/10+FEEDERS!$G$19 -> 31.975 | H83: C | I83: =+(G83*C83)/100 -> 0 | J83: =+(((I83*$I$324)+(F83*(1+$E$324)))*(1+$C$330)) -> 0 | K83: =IF(J83=0,0,J83/C83) -> 0
B84: 2- 250 AL feed (ft) | D84: =((FEEDERS!$D$113*4)/10+FEEDERS!$D$16)*2 -> 3145.84 | E84: C | F84: =+(D84*C84)/100 -> 0 | G84: =((FEEDERS!$G$113*4)/10+FEEDERS!$G$16)*2 -> 40.2 | H84: C | I84: =+(G84*C84)/100 -> 0 | J84: =+(((I84*$I$324)+(F84*(1+$E$324)))*(1+$C$330)) -> 0 | K84: =IF(J84=0,0,J84/C84) -> 0
B85: 750 AL feed (ft) | D85: =(FEEDERS!$D$119*4)/10+FEEDERS!$D$19 -> 3091.89 | E85: C | F85: =+(D85*C85)/100 -> 0 | G85: =(FEEDERS!$G$119*4)/10+FEEDERS!$G$19 -> 31.575 | H85: C | I85: =+(G85*C85)/100 -> 0 | J85: =+(((I85*$I$324)+(F85*(1+$E$324)))*(1+$C$330)) -> 0 | K85: =IF(J85=0,0,J85/C85) -> 0
A86: 150 KVA transformer | D86: 5000 | E86: E | F86: =+D86*C86 -> 0 | G86: 15 | H86: E | I86: =+G86*C86 -> 0 | J86: =+(((I86*$I$324)+(F86*(1+$E$324)))*(1+$C$330)) -> 0 | K86: =IF(J86=0,0,J86/C86) -> 0
B87: CU feed (ft) | D87: =(FEEDERS!$D$94*3)/10+FEEDERS!$D$16 -> 2702.09 | E87: C | F87: =+(D87*C87)/100 -> 0 | G87: =(FEEDERS!$G$94*3)/10+FEEDERS!$G$16 -> 17.8 | H87: C | I87: =+(G87*C87)/100 -> 0 | J87: =+(((I87*$I$324)+(F87*(1+$E$324)))*(1+$C$330)) -> 0 | K87: =IF(J87=0,0,J87/C87) -> 0
B88: AL feed (ft) | D88: =(FEEDERS!$D$114*3)/10+FEEDERS!$D$16 -> 1592.975 | E88: C | F88: =+(D88*C88)/100 -> 0 | G88: =(FEEDERS!$G$114*3)/10+FEEDERS!$G$16 -> 18.4 | H88: C | I88: =+(G88*C88)/100 -> 0 | J88: =+(((I88*$I$324)+(F88*(1+$E$324)))*(1+$C$330)) -> 0 | K88: =IF(J88=0,0,J88/C88) -> 0
A89: 112.5KVA transformer | D89: 4000 | E89: E | F89: =+D89*C89 -> 0 | G89: 13 | H89: E | I89: =+G89*C89 -> 0 | J89: =+(((I89*$I$324)+(F89*(1+$E$324)))*(1+$C$330)) -> 0 | K89: =IF(J89=0,0,J89/C89) -> 0
B90: CU feed (ft) | D90: =(FEEDERS!$D$91*3)/10+FEEDERS!$D$14 -> 1486.275 | E90: C | F90: =+(D90*C90)/100 -> 0 | G90: =(FEEDERS!$G$91*3)/10+FEEDERS!$G$14 -> 13.442 | H90: C | I90: =+(G90*C90)/100 -> 0 | J90: =+(((I90*$I$324)+(F90*(1+$E$324)))*(1+$C$330)) -> 0 | K90: =IF(J90=0,0,J90/C90) -> 0
B91: AL feed (ft) | D91: =(FEEDERS!$D$111*3)/10+FEEDERS!$D$15 -> 1003.995 | E91: C | F91: =+(D91*C91)/100 -> 0 | G91: =(FEEDERS!$G$111*3)/10+FEEDERS!$G$15 -> 15.713 | H91: C | I91: =+(G91*C91)/100 -> 0 | J91: =+(((I91*$I$324)+(F91*(1+$E$324)))*(1+$C$330)) -> 0 | K91: =IF(J91=0,0,J91/C91) -> 0
A92: 75KVA transformer | D92: 3500 | E92: E | F92: =+D92*C92 -> 0 | G92: 13 | H92: E | I92: =+G92*C92 -> 0 | J92: =+(((I92*$I$324)+(F92*(1+$E$324)))*(1+$C$330)) -> 0 | K92: =IF(J92=0,0,J92/C92) -> 0
B93: CU feed (ft) | D93: =(FEEDERS!$D$90*3)/10+FEEDERS!$D$13 -> 1214.43 | E93: C | F93: =+(D93*C93)/100 -> 0 | G93: =(FEEDERS!$G$90*3)/10+FEEDERS!$G$13 -> 11.482 | H93: C | I93: =+(G93*C93)/100 -> 0 | J93: =+(((I93*$I$324)+(F93*(1+$E$324)))*(1+$C$330)) -> 0 | K93: =IF(J93=0,0,J93/C93) -> 0
B94: AL feed (ft) | D94: =(FEEDERS!$D$110*3)/10+FEEDERS!$D$14 -> 866.04 | E94: C | F94: =+(D94*C94)/100 -> 0 | G94: =(FEEDERS!$G$110*3)/10+FEEDERS!$G$14 -> 13.742 | H94: C | I94: =+(G94*C94)/100 -> 0 | J94: =+(((I94*$I$324)+(F94*(1+$E$324)))*(1+$C$330)) -> 0 | K94: =IF(J94=0,0,J94/C94) -> 0
A95: 45KVA transformer | D95: 2500 | E95: E | F95: =+D95*C95 -> 0 | G95: 12 | H95: E | I95: =+G95*C95 -> 0 | J95: =+(((I95*$I$324)+(F95*(1+$E$324)))*(1+$C$330)) -> 0 | K95: =IF(J95=0,0,J95/C95) -> 0
B96: CU feed (ft) | D96: =(FEEDERS!$D$87*3)/10+FEEDERS!$D$12 -> 731.3 | E96: C | F96: =+(D96*C96)/100 -> 0 | G96: =(FEEDERS!$G$87*3)/10+FEEDERS!$G$12 -> 9.488 | H96: C | I96: =+(G96*C96)/100 -> 0 | J96: =+(((I96*$I$324)+(F96*(1+$E$324)))*(1+$C$330)) -> 0 | K96: =IF(J96=0,0,J96/C96) -> 0
B97: AL feed (ft) | D97: 250 | E97: C | F97: =+(D97*C97)/100 -> 0 | G97: 9 | H97: C | I97: =+(G97*C97)/100 -> 0 | J97: =+(((I97*$I$324)+(F97*(1+$E$324)))*(1+$C$330)) -> 0 | K97: =IF(J97=0,0,J97/C97) -> 0
A98: 30KVA transformer | D98: 2000 | E98: E | F98: =+D98*C98 -> 0 | G98: 10 | H98: E | I98: =+G98*C98 -> 0 | J98: =+(((I98*$I$324)+(F98*(1+$E$324)))*(1+$C$330)) -> 0 | K98: =IF(J98=0,0,J98/C98) -> 0
B99: CU feed (ft) | D99: =(FEEDERS!$D$86*3)/10+FEEDERS!$D$11 -> 458.05 | E99: C | F99: =+(D99*C99)/100 -> 0 | G99: =(FEEDERS!$G$86*3)/10+FEEDERS!$G$11 -> 7.06 | H99: C | I99: =+(G99*C99)/100 -> 0 | J99: =+(((I99*$I$324)+(F99*(1+$E$324)))*(1+$C$330)) -> 0 | K99: =IF(J99=0,0,J99/C99) -> 0
B100: AL feed (ft) | D100: 150 | E100: C | F100: =+(D100*C100)/100 -> 0 | G100: 6 | H100: C | I100: =+(G100*C100)/100 -> 0 | J100: =+(((I100*$I$324)+(F100*(1+$E$324)))*(1+$C$330)) -> 0 | K100: =IF(J100=0,0,J100/C100) -> 0
...

Sheet Site
A1: STREETLIGHTING ESTIMATOR
A2: ESTIMATE #
A4: MATERIAL | B4: QTY | C4: MAT UNIT | D4: per | E4: EXTENSION | F4: LBR UNIT | G4: per | H4: EXTENSION
A6: Lighting Quote | B6: 1 | C6: =L15 -> 0 | D6: E | E6: =B6*C6 -> 0 | F6: 0 | G6: E | H6: =B6*F6 -> 0 | I6: =((((H6*$H$62)+(E6*(1+$C$62)))*(1+$B$67))*(1+$B$72)) -> 0 | J6: =IF(I6=0,0,I6/B6) -> 0
A7: S1 - Bollard | B7: 0 | C7: 50 | D7: E | E7: =B7*C7 -> 0 | F7: 5 | G7: E | H7: =B7*F7 -> 0 | I7: =((((H7*$H$62)+(E7*(1+$C$62)))*(1+$B$67))*(1+$B$72)) -> 0 | J7: =IF(I7=0,0,I7/B7) -> 0 | K7: 0 | L7: =K7*B7 -> 0
A8: S2 Light (One head) | B8: 0 | C8: 50 | D8: E | E8: =B8*C8 -> 0 | F8: 7 | G8: E | H8: =B8*F8 -> 0 | I8: =((((H8*$H$62)+(E8*(1+$C$62)))*(1+$B$67))*(1+$B$72)) -> 0 | J8: =IF(I8=0,0,I8/B8) -> 0 | K8: 0 | L8: =K8*B8 -> 0
A9: S6 Light (Two head) | B9: 0 | C9: 75 | D9: E | E9: =B9*C9 -> 0 | F9: 8.5 | G9: E | H9: =B9*F9 -> 0 | I9: =((((H9*$H$62)+(E9*(1+$C$62)))*(1+$B$67))*(1+$B$72)) -> 0 | J9: =IF(I9=0,0,I9/B9) -> 0 | K9: 0 | L9: =K9*B9 -> 0
A10: S7 Light (Three head) | B10: 0 | C10: 100 | D10: E | E10: =B10*C10 -> 0 | F10: 10 | G10: E | H10: =B10*F10 -> 0 | I10: =((((H10*$H$62)+(E10*(1+$C$62)))*(1+$B$67))*(1+$B$72)) -> 0 | J10: =IF(I10=0,0,I10/B10) -> 0 | K10: 0 | L10: =K10*B10 -> 0
A11: S7 Light (Four head) | B11: 0 | C11: 125 | D11: E | E11: =B11*C11 -> 0 | F11: 11.5 | G11: E | H11: =B11*F11 -> 0 | I11: =((((H11*$H$62)+(E11*(1+$C$62)))*(1+$B$67))*(1+$B$72)) -> 0 | J11: =IF(I11=0,0,I11/B11) -> 0 | K11: 0 | L11: =K11*B11 -> 0
A12: S8 Wall Pack | B12: 0 | C12: 50 | D12: E | E12: =B12*C12 -> 0 | F12: 5 | G12: E | H12: =B12*F12 -> 0 | I12: =((((H12*$H$62)+(E12*(1+$C$62)))*(1+$B$67))*(1+$B$72)) -> 0 | J12: =IF(I12=0,0,I12/B12) -> 0 | K12: 0 | L12: =K12*B12 -> 0
A13: Concrete base 2' X6' | B13: =SUM(B8:B11) -> 0 | C13: 500 | D13: E | E13: =B13*C13 -> 0 | F13: 8 | G13: E | H13: =B13*F13 -> 0 | I13: =((((H13*$H$62)+(E13*(1+$C$62)))*(1+$B$67))*(1+$B$72)) -> 0 | J13: =IF(I13=0,0,I13/B13) -> 0 | K13: SUB-TOTAL | L13: =SUM(L7:L12) -> 0
A14: Concrete base 12" X4' | B14: =B7 -> 0 | C14: 150 | D14: E | E14: =B14*C14 -> 0 | F14: 4 | G14: E | H14: =B14*F14 -> 0 | I14: =((((H14*$H$62)+(E14*(1+$C$62)))*(1+$B$67))*(1+$B$72)) -> 0 | J14: =IF(I14=0,0,I14/B14) -> 0 | K14: 0.05 | L14: =L13*K14 -> 0
A15: Helex 8" x 6' Chance T112 | B15: 0 | C15: 400 | D15: E | E15: =B15*C15 -> 0 | F15: 3 | G15: E | H15: =B15*F15 -> 0 | I15: =((((H15*$H$62)+(E15*(1+$C$62)))*(1+$B$67))*(1+$B$72)) -> 0 | J15: =IF(I15=0,0,I15/B15) -> 0 | K15: TOTAL | L15: =L14+L13 -> 0
A16: Fusing | B16: =B13+B14 -> 0 | C16: 20 | D16: E | E16: =B16*C16 -> 0 | F16: 0.15 | G16: E | H16: =B16*F16 -> 0 | I16: =((((H16*$H$62)+(E16*(1+$C$62)))*(1+$B$67))*(1+$B$72)) -> 0 | J16: =IF(I16=0,0,I16/B16) -> 0
A17: Grounding | B17: =B13+B14 -> 0 | C17: 35 | D17: E | E17: =B17*C17 -> 0 | F17: 0.3 | G17: E | H17: =B17*F17 -> 0 | I17: =((((H17*$H$62)+(E17*(1+$C$62)))*(1+$B$67))*(1+$B$72)) -> 0 | J17: =IF(I17=0,0,I17/B17) -> 0
A18: Trenching | B18: 0 | C18: 2 | D18: FT | E18: =B18*C18 -> 0 | F18: 8 | G18: C | H18: =B18*F18/100 -> 0 | I18: =((((H18*$H$62)+(E18*(1+$C$62)))*(1+$B$67))*(1+$B$72)) -> 0 | J18: =IF(I18=0,0,I18/B18) -> 0
A19: 1" GRC | B19: 0 | C19: 250 | D19: C | E19: =B19*C19/100 -> 0 | F19: 5 | G19: C | H19: =B19*F19/100 -> 0 | I19: =((((H19*$H$62)+(E19*(1+$C$62)))*(1+$B$67))*(1+$B$72)) -> 0 | J19: =IF(I19=0,0,I19/B19) -> 0
A20: 1-1/4" GRC | B20: 0 | C20: 350 | D20: C | E20: =B20*C20/100 -> 0 | F20: 5.5 | G20: C | H20: =B20*F20/100 -> 0 | I20: =((((H20*$H$62)+(E20*(1+$C$62)))*(1+$B$67))*(1+$B$72)) -> 0 | J20: =IF(I20=0,0,I20/B20) -> 0
A21: 1-1/2 GRC | B21: 0 | C21: 425 | D21: C | E21: =B21*C21/100 -> 0 | F21: 6.75 | G21: C | H21: =B21*F21/100 -> 0 | I21: =((((H21*$H$62)+(E21*(1+$C$62)))*(1+$B$67))*(1+$B$72)) -> 0 | J21: =IF(I21=0,0,I21/B21) -> 0
A22: 2" GRC | B22: 0 | C22: 500 | D22: C | E22: =B22*C22/100 -> 0 | F22: 7.75 | G22: C | H22: =B22*F22/100 -> 0 | I22: =((((H22*$H$62)+(E22*(1+$C$62)))*(1+$B$67))*(1+$B$72)) -> 0 | J22: =IF(I22=0,0,I22/B22) -> 0
A23: 3" GRC | B23: 0 | C23: 1100 | D23: C | E23: =B23*C23/100 -> 0 | F23: 12.25 | G23: C | H23: =B23*F23/100 -> 0 | I23: =((((H23*$H$62)+(E23*(1+$C$62)))*(1+$B$67))*(1+$B$72)) -> 0 | J23: =IF(I23=0,0,I23/B23) -> 0
A24: 4'' GRC | B24: 0 | C24: 1525 | D24: C | E24: =B24*C24/100 -> 0 | F24: 17.25 | G24: C | H24: =B24*F24/100 -> 0 | I24: =((((H24*$H$62)+(E24*(1+$C$62)))*(1+$B$67))*(1+$B$72)) -> 0 | J24: =IF(I24=0,0,I24/B24) -> 0
A25: 1" IMC | B25: 0 | C25: 180 | D25: C | E25: =B25*C25/100 -> 0 | F25: 5 | G25: C | H25: =B25*F25/100 -> 0 | I25: =((((H25*$H$62)+(E25*(1+$C$62)))*(1+$B$67))*(1+$B$72)) -> 0 | J25: =IF(I25=0,0,I25/B25) -> 0
A26: 1-1/4 IMC | B26: 0 | C26: 240 | D26: C | E26: =B26*C26/100 -> 0 | F26: 5.5 | G26: C | H26: =B26*F26/100 -> 0 | I26: =((((H26*$H$62)+(E26*(1+$C$62)))*(1+$B$67))*(1+$B$72)) -> 0 | J26: =IF(I26=0,0,I26/B26) -> 0
A27: 1-1/2 IMC | B27: 0 | C27: 310 | D27: C | E27: =B27*C27/100 -> 0 | F27: 7 | G27: C | H27: =B27*F27/100 -> 0 | I27: =((((H27*$H$62)+(E27*(1+$C$62)))*(1+$B$67))*(1+$B$72)) -> 0 | J27: =IF(I27=0,0,I27/B27) -> 0
A28: 2 IMC | B28: 0 | C28: 390 | D28: C | E28: =B28*C28/100 -> 0 | F28: 8 | G28: C | H28: =B28*F28/100 -> 0 | I28: =((((H28*$H$62)+(E28*(1+$C$62)))*(1+$B$67))*(1+$B$72)) -> 0 | J28: =IF(I28=0,0,I28/B28) -> 0
A29: 3" IMC | B29: 0 | C29: 950 | D29: C | E29: =B29*C29/100 -> 0 | F29: 12 | G29: C | H29: =B29*F29/100 -> 0 | I29: =((((H29*$H$62)+(E29*(1+$C$62)))*(1+$B$67))*(1+$B$72)) -> 0 | J29: =IF(I29=0,0,I29/B29) -> 0
A30: 4'' IMC | B30: 0 | C30: 1300 | D30: C | E30: =B30*C30/100 -> 0 | F30: 16.5 | G30: C | H30: =B30*F30/100 -> 0 | I30: =((((H30*$H$62)+(E30*(1+$C$62)))*(1+$B$67))*(1+$B$72)) -> 0 | J30: =IF(I30=0,0,I30/B30) -> 0
... A53: Spoils stockpile | B53: 0 | C53: 75 | D53: C | E53: =B53*C53/100 -> 0 | F53: 2 | G53: C | H53: =B53*F53/100 -> 0 | I53: =((((H53*$H$62)+(E53*(1+$C$62)))*(1+$B$67))*(1+$B$72)) -> 0 | J53: =IF(I53=0,0,I53/B53) -> 0
A54: Spoil removal | B54: 0 | C54: 250 | D54: Y | E54: =SUM(B54*0.5*3/27)*C54/13 -> 0 | F54: 0.35 | G54: Y | H54: =B54*F54 -> 0 | I54: =((((H54*$H$62)+(E54*(1+$C$62)))*(1+$B$67))*(1+$B$72)) -> 0 | J54: =IF(I54=0,0,I54/B54) -> 0
A55: Concrete | B55: 0 | C55: 90 | D55: Y | E55: =(B55*0.5*0.5/27)*C55 -> 0 | F55: 0.25 | G55: Y | H55: =B55*F55 -> 0 | I55: =((((H55*$H$62)+(E55*(1+$C$62)))*(1+$B$67))*(1+$B$72)) -> 0 | J55: =IF(I55=0,0,I55/B55) -> 0
A56: Quazite box | B56: 0 | C56: 500 | D56: E | E56: =(B56/27)*C56 -> 0 | F56: 4 | G56: E | H56: =B56*F56 -> 0 | I56: =((((H56*$H$62)+(E56*(1+$C$62)))*(1+$B$67))*(1+$B$72)) -> 0 | J56: =IF(I56=0,0,I56/B56) -> 0
A57: Bucket truck | B57: 0 | C57: 38 | D57: HR | E57: =B57*C57 -> 0 | F57: 0 | G57: HR | H57: =B57*F57 -> 0 | I57: =((((H57*$H$62)+(E57*(1+$C$62)))*(1+$B$67))*(1+$B$72)) -> 0 | J57: =IF(I57=0,0,I57/B57) -> 0
A58: Bucket truck w/operator | B58: 0 | C58: 38 | D58: HR | E58: =B58*C58 -> 0 | F58: 1 | G58: HR | H58: =B58*F58 -> 0 | I58: =((((H58*$H$62)+(E58*(1+$C$62)))*(1+$B$67))*(1+$B$72)) -> 0 | J58: =IF(I58=0,0,I58/B58) -> 0
A59: Boring, underground drilling | C59: 2.79 | D59: FT | E59: =B59*C59 -> 0 | F59: 0.25 | G59: FT | H59: =B59*F59 -> 0 | I59: =((((H59*$H$62)+(E59*(1+$C$62)))*(1+$B$67))*(1+$B$72)) -> 0 | J59: =IF(I59=0,0,I59/B59) -> 0
A60: Equipment maintenance | B60: 0 | C60: 1000 | D60: LOT | E60: =B60*C60 -> 0 | F60: 18 | G60: LOT | H60: =B60*F60 -> 0 | I60: =((((H60*$H$62)+(E60*(1+$C$62)))*(1+$B$67))*(1+$B$72)) -> 0 | J60: =IF(I60=0,0,I60/B60) -> 0
A61: SUBTOTAL | E61: =SUM(E6:E60) -> 0 | H61: =SUM(H6:H60) -> 0
C62: 0.1025 | D62: Tax | E62: =SUM(E61)*C62 -> 0 | F62: Hourly | G62: Cost | H62: 79
E63: =SUM(E61:E62) -> 0 | H63: =H61*H62 -> 0 | I63: =SUM(I4:I62) -> 0
A64: TOTAL MATERIAL | C64: =E63 -> 0 | D64: This streetlighting estimator is set up for commercial work. There may be need to alter the price for residential work. Labor cost is entered in cell H60 and automatically altered on the Job Set-Up sheet. All amounts in the yellow box are automatically transferred there also. The total estimated price needs to be manually entered on the Quote sheet.
A65: TOTAL LABOR | C65: =H63 -> 0
A66: TOTAL MATERIAL + LABOR | C66: =SUM(C64:C65) -> 0
A67: OVERHEAD | B67: 0 | C67: =C66*B67 -> 0
A68: SUB TOTAL | C68: =SUM(C66:C67) -> 0
A69: RENTAL EQUIPMENT | C69: 0
A70: SUBCONTRACTS | C70: 0
A71: SUB TOTAL | C71: =SUM(C68:C70) -> 0
A72: PROFIT | B72: 0 | C72: =C71*B72 -> 0
A73: PROJECT TOTALS | C73: =SUM(C71:C72) -> 0
A74: # of poles
A75: PRICE PER POLE | C75: =C73/C74 -> #DIV/0!

Sheet PROPOSAL
E4: 817 S Kildare Ave
E5: Chicago, Illinois 60624
E6: Phone: 773.826.2600 Fax: 773.826.2620
E8: =basebid!F2 -> Todays Date
A10: =basebid!A5 -> Contact Name | E10: RE: | F10: =basebid!A2 -> Elevator/Lobby/Corridors & Vacant Suite 3450
A11: =basebid!A4 -> G.C. | F11: =basebid!A3 -> 120 N LaSalle
A12: =basebid!A6 -> Telephone - Fax | E12: Est# | F12: =basebid!D2 -> KM05
A14: We have prepared an electrical estimate regarding the above project.
A15: Our proposal is based on information and drawings provided.
A17: We have included the following items in our proposal.
A19: =-basebid!C11 -> 0 | B19: =basebid!A11 -> TEMP POWER | D19: =-basebid!C159 -> 0 | E19: =basebid!A159 -> MECHANICAL CONNECTIONS
A20: =-basebid!C12 -> 0 | B20: =basebid!A12 -> Temp power from ComEd permanent power | D20: =-basebid!C160 -> 0 | E20: =basebid!A160 -> Make Up Air Units - gas (warehouse)
A21: =-basebid!C13 -> 0 | B21: =basebid!A13 -> Hook up of construction trailer | D21: =-basebid!C161 -> 0 | E21: =basebid!A161 -> Roof Top Unit - gas (office)
A22: =-basebid!C14 -> 0 | B22: =basebid!A14 -> 0 | D22: =-basebid!C162 -> 0 | E22: =basebid!A162 -> Electric water heaters
A23: =-basebid!C15 -> 0 | B23: =basebid!A15 -> ELECTRICAL SERVICE & DISTRIBUTION | D23: =-basebid!C163 -> 0 | E23: =basebid!A163 -> 200 Amp Fire pump w/ 30' feed and meter
A24: =-basebid!C16 -> 0 | B24: =basebid!A16 -> ComEd pad | D24: =-basebid!C164 -> 0 | E24: =basebid!A164 -> Jockey pump
A25: =-basebid!C17 -> 0 | B25: =basebid!A17 -> Rework existing panel for new loads | D25: =-basebid!C165 -> 0 | E25: =basebid!A165 -> Hydraulic elevator
A26: =-basebid!C18 -> 0 | B26: =basebid!A18 -> 4000A., 277/480V., 3PH. Main switchboard w/ meter | D26: =-basebid!C166 -> 0 | E26: =basebid!A166 -> Exhaust Fan with Interlock Conduit
A27: =-basebid!C19 -> 0 | B27: =basebid!A19 -> 0 | D27: =-basebid!C167 -> 0 | E27: =basebid!A167 -> Unit Heater (gas)
A28: =-basebid!#REF! -> #REF! | B28: =basebid!#REF! -> #REF! | D28: =-basebid!C168 -> 0 | E28: =basebid!A168 -> Electric Wall heater (FBO)
A29: =-basebid!C21 -> 0 | B29: =basebid!A21 -> 3000A., 277/480V., 3PH. Main switchboard w/ meter | D29: =-basebid!C169 -> 0 | E29: =basebid!A169 -> Baseboard Heater (FBO)
A30: =-basebid!C22 -> 0 | B30: =basebid!A22 -> 0 | D30: =-basebid!C170 -> 0 | E30: =basebid!A170 -> Toilet Exhaust (FBO)
A31: =-basebid!#REF! -> #REF! | B31: =basebid!#REF! -> #REF! | D31: =-basebid!C171 -> 0 | E31: =basebid!A171 -> Sump Pump
A32: =-basebid!C24 -> 0 | B32: =basebid!A24 -> 2500A., 277/480V., 3PH. Main switchboard w/ meter | D32: =-basebid!C172 -> 0 | E32: =basebid!A172 -> 30A Equipment connection
A33: =-basebid!C25 -> 0 | B33: =basebid!A25 -> 0 | D33: =-basebid!C173 -> 0 | E33: =basebid!A173 -> 0
A34: =-basebid!#REF! -> #REF! | B34: =basebid!#REF! -> #REF! | D34: =-basebid!C174 -> 0 | E34: =basebid!A174 -> 40A Equipment connection
A35: =-basebid!C27 -> 0 | B35: =basebid!A27 -> 2000A., 277/480V., 3PH. Main switchboard w/ meter | D35: =-basebid!C175 -> 0 | E35: =basebid!A175 -> 0
A36: =-basebid!C28 -> 0 | B36: =basebid!A28 -> 0 | D36: =-basebid!C176 -> 0 | E36: =basebid!A176 -> 60A Equipment connection
A37: =-basebid!#REF! -> #REF! | B37: =basebid!#REF! -> #REF! | D37: =-basebid!C177 -> 0 | E37: =basebid!A177 -> 0
A38: =-basebid!C30 -> 0 | B38: =basebid!A30 -> 1600A., 277/480V., 3PH. Main switchboard w/ meter | D38: =-basebid!C178 -> 0 | E38: =basebid!A178 -> 100A Equipment connection
A39: =-basebid!C31 -> 0 | B39: =basebid!A31 -> 0 | D39: =-basebid!C179 -> 0 | E39: =basebid!A179 -> 0
A40: =-basebid!#REF! -> #REF! | B40: =basebid!#REF! -> #REF! | D40: =-basebid!C180 -> 0 | E40: =basebid!A180 -> 200A Equipment connection
A41: =-basebid!C33 -> 0 | B41: =basebid!A33 -> 1200A., 277/480V., 3PH. Main distribution board w/ ct/meter | D41: =-basebid!C181 -> 0 | E41: =basebid!A181 -> 0
A42: =-basebid!C34 -> 0 | B42: =basebid!A34 -> 0 | D42: =-basebid!C182 -> 0 | E42: =basebid!A182 -> 400A Equipment connection
A43: =-basebid!#REF! -> #REF! | B43: =basebid!#REF! -> #REF! | D43: =-basebid!C183 -> 0 | E43: =basebid!A183 -> 0
A44: =-basebid!C36 -> 0 | B44: =basebid!A36 -> 1000A., 277/480V., 3PH. Main distribution board w/ ct/meter | D44: =-basebid!C184 -> 0 | E44: =basebid!A184 -> 600A.Equipment connection
A45: =-basebid!C37 -> 0 | B45: =basebid!A37 -> 0 | D45: =-basebid!C185 -> 0 | E45: =basebid!A185 -> 0
A46: =-basebid!#REF! -> #REF! | B46: =basebid!#REF! -> #REF! | D46: =-basebid!C186 -> 0 | E46: =basebid!A186 -> 800A.Equipment connection
A47: =-basebid!C39 -> 0 | B47: =basebid!A39 -> 800A., 277/480V., 3PH. Distribution board w/ feed | D47: =-basebid!C187 -> 0 | E47: =basebid!A187 -> 0
A48: =-basebid!C40 -> 0 | B48: =basebid!A40 -> 0 | D48: =-basebid!C188 -> 0 | E48: =basebid!A188 -> 1200A.Equipment connection
D49: =-basebid!C189 -> 0 | E49: =basebid!A189 -> 0
A53: Our price for this Work: | C53: =basebid!D331 -> 0
A55: Items not included in our proposal are as follows:
A56: - | B56: Permit or bond fees.
A57: - | B57: Dumpster fees
A58: - | B58: Excess utility company facility charges.
A59: - | B59: Spoil removal
A60: - | B60: Any low voltage cabling, equipment, or devices whatsoever, except fire alarm.
A61: - | B61: Any site sleeving is excluded
A62: - | B62: Any temperature control wiring, starters, or mechanical equipment
A63: - | B63: Any coring, sawcutting, or patching is excluded unless noted above.
A64: - | B64: Concrete encasements and pads have been excluded unless noted.
A65: - | B65: Mechanical equipment, starters, or like materials associated with equipment unless noted otherwise
A66: - | B66: Premium time is excluded.
A67: - | B67: Additional Labor and Material authorized by code/village inspector and authorities.
... A69: - | B69: Due to material price increases, this proposal is good for 30 days from date above.
A71: Best Regards,
A74: John Gavula
A75: ABCO Electrical Construction and Design
